Workbook

Sheet SET-UP & SUMMARY
A1: SUMMARY - NPO PAYOUT - AP
A3: PAYOUT EVENT DETAILS - SETUP
A4: Event Date: | B4: 46270
A5: Event Day of Week: | B5: =B4 -> 46270
A6: Event Description: | B6: Football
A10: SUMMARY REPORT — ASSIGNMENT-DRIVEN
A11: NPO | B11: ASSIGNMENT SALES | C11: CONTRACT DONATION | D11: TIPS | E11: TOTAL PAYOUT*
A12: ARVC | B12: =SUMIFS('CONTRACT CALC'!$J$13:$J$112,'CONTRACT CALC'!$B$13:$B$112,A12) -> 48024 | C12: =SUMIFS('CONTRACT CALC'!$K$13:$K$112,'CONTRACT CALC'!$B$13:$B$112,A12) -> 4486.82 | D12: =SUMIFS('TIPS DATA'!$H$2:$H$101,'TIPS DATA'!$C$2:$C$101,A12) -> 3421.74 | E12: =C12+D12 -> 7908.56
A13: AIRFORCE | B13: =SUMIFS('CONTRACT CALC'!$J$13:$J$112,'CONTRACT CALC'!$B$13:$B$112,A13) -> 0 | C13: =SUMIFS('CONTRACT CALC'!$K$13:$K$112,'CONTRACT CALC'!$B$13:$B$112,A13) -> 0 | D13: =SUMIFS('TIPS DATA'!$H$2:$H$101,'TIPS DATA'!$C$2:$C$101,A13) -> 0 | E13: =C13+D13 -> 0
A14: UNITED FIT | B14: =SUMIFS('CONTRACT CALC'!$J$13:$J$112,'CONTRACT CALC'!$B$13:$B$112,A14) -> 0 | C14: =SUMIFS('CONTRACT CALC'!$K$13:$K$112,'CONTRACT CALC'!$B$13:$B$112,A14) -> 0 | D14: =SUMIFS('TIPS DATA'!$H$2:$H$101,'TIPS DATA'!$C$2:$C$101,A14) -> 0 | E14: =C14+D14 -> 0
A15: DCVA | B15: =SUMIFS('CONTRACT CALC'!$J$13:$J$112,'CONTRACT CALC'!$B$13:$B$112,A15) -> 0 | C15: =SUMIFS('CONTRACT CALC'!$K$13:$K$112,'CONTRACT CALC'!$B$13:$B$112,A15) -> 0 | D15: =SUMIFS('TIPS DATA'!$H$2:$H$101,'TIPS DATA'!$C$2:$C$101,A15) -> 0 | E15: =C15+D15 -> 0
A16: DEL N CHEER | B16: =SUMIFS('CONTRACT CALC'!$J$13:$J$112,'CONTRACT CALC'!$B$13:$B$112,A16) -> 0 | C16: =SUMIFS('CONTRACT CALC'!$K$13:$K$112,'CONTRACT CALC'!$B$13:$B$112,A16) -> 0 | D16: =SUMIFS('TIPS DATA'!$H$2:$H$101,'TIPS DATA'!$C$2:$C$101,A16) -> 0 | E16: =C16+D16 -> 0
A17: RIO GRANDE RGHS | B17: =SUMIFS('CONTRACT CALC'!$J$13:$J$112,'CONTRACT CALC'!$B$13:$B$112,A17) -> 0 | C17: =SUMIFS('CONTRACT CALC'!$K$13:$K$112,'CONTRACT CALC'!$B$13:$B$112,A17) -> 0 | D17: =SUMIFS('TIPS DATA'!$H$2:$H$101,'TIPS DATA'!$C$2:$C$101,A17) -> 0 | E17: =C17+D17 -> 0
A18: VICTORY OUTREACH | B18: =SUMIFS('CONTRACT CALC'!$J$13:$J$112,'CONTRACT CALC'!$B$13:$B$112,A18) -> 6694.5 | C18: =SUMIFS('CONTRACT CALC'!$K$13:$K$112,'CONTRACT CALC'!$B$13:$B$112,A18) -> 643.12 | D18: =SUMIFS('TIPS DATA'!$H$2:$H$101,'TIPS DATA'!$C$2:$C$101,A18) -> 0 | E18: =C18+D18 -> 643.12
A19: TOTAL | B19: =SUM(B12:B18) -> 54718.5 | C19: =SUM(C12:C18) -> 5129.94 | D19: =SUM(D12:D18) -> 3421.74 | E19: =SUM(E12:E18) -> 8551.68
A21: VENDOR PAYOUT is the reusable settlement OUTPUT controlled by Event Date + Payee/NPO. Update source data, select Event + Payee on VENDOR PAYOUT, review, export PDF. One-way only: SOURCE → CALCULATION → OUTPUT.
A23: SETUP - STAND LOCATIONS
A24: STAND ID | B24: STAND DESCRIPTION
A25: BASEBALL | B25: TRAILER | C25: baseball
A26: 207 - PREM | B26: DESSERT CART | C26: PIT
A27: PREM 000 | B27: PREMIUM BANQUET | C27: PIT
A28: FB 100 | B28: TRAILER N CONCOURSE | C28: FB
A29: FB 100B | B29: MBP TRAILER N CONCOURSE | C29: FB
A30: FB 101 | B30: STADIUM SIPS SHACK SW | C30: FB
A31: FB 102 | B31: TOWER SOUTH | C31: FB
A32: FB 103 | B32: TOWER NORTH | C32: FB
A33: FB 104 | B33: RED RALLY NORTH WEST | C33: FB
A34: FB 105 | B34: NW SPECIALTY DAWG 2.0 | C34: FB
A35: FB 106 | B35: RED RALLY NORTH EAST | C35: FB
A36: FB 107 | B36: NE SPECIALTY DAWG O.G. | C36: FB
... A80: PIT CU1 | B80: CULINARY SUPPORT | C80: PIT

Sheet VENDOR PAYOUT
C2: SETTLEMENT STATEMENT
C3: LEVY • UNM ATHLETICS
B5: =$E$10 -> ARVC | G5: TOTAL PAYABLE
B6: ='SET-UP & SUMMARY'!B6 -> Football | G6: =SUM(H33,I33,I36,I37,I38,I39,I40,I41) -> 7908.56
B9: EVENT DATE | C9: INVOICE | E9: PAYEE / NPO | G9: SAP ID | H9: BSS ID
B10: 46270 | C10: =CONCATENATE("UNM-",TEXT(B10,"MMDDYY-"),E10) -> UNM-090526-ARVC | E10: ARVC
B11: Controls: Event Date (B10) + Payee/NPO (E10). Location rows filter from EVENT ASSIGNMENT via CONTRACT CALC. Flow: SOURCE → CALCULATION → OUTPUT (never reverse).
B12: SALES COMMISSION (DONATION TO NPO): POS SALES | E12: NON-CALCULATED SALES DATA
B13: FOOD / NON-ALCOHOLIC | C13: ALCOHOL | D13: GROUP NET | E13: SALES TAX | F13: GROSS SALES
B14: =D33 -> 32245 | C14: =F33 -> 15779 | D14: =C33 -> 48024 | E14: =D33 -> 32245 | F14: =E33 -> 3224.5
B16: LOCATION SERVICE DETAIL
A17: # | B17: SERVICE AREA | C17: NET SALES | D17: FOOD / NON-ALC NET SALES | E17: 10% FOOD / NON-ALC COMMISSION | F17: ALCOHOL NET SALES | G17: 8% ALCOHOL COMMISSION | H17: TOTAL COMMISSION | I17: GRATUITIES
A18: =IFERROR(MATCH(TEXT($B$10,"yyyymmdd")&"|"&$E$10&"|1",'EVENT ASSIGNMENT'!$K$2:$K$101,0),"") -> 1 | B18: =IF(IFERROR(MATCH(TEXT($B$10,"yyyymmdd")&"|"&$E$10&"|1",'EVENT ASSIGNMENT'!$K$2:$K$101,0),"")="","",IFERROR(INDEX('EVENT ASSIGNMENT'!$D$2:$D$101,IFERROR(MATCH(TEXT($B$10,"yyyymmdd")&"|"&$E$10&"|1",'EVENT ASSIGNMENT'!$K$2:$K$101,0),"")),"")) -> RED RALLY NORTH EAST | C18: =IF(OR(IFERROR(MATCH(TEXT($B$10,"yyyymmdd")&"|"&$E$10&"|1",'EVENT ASSIGNMENT'!$K$2:$K$101,0),"")="",B18=""),"",IFERROR(INDEX('CONTRACT CALC'!$G$13:$G$112,IFERROR(MATCH(TEXT($B$10,"yyyymmdd")&"|"&$E$10&"|1",'EVENT ASSIGNMENT'!$K$2:$K$101,0),""))*INDEX('CONTRACT CALC'!$F$13:$F$112,IFERROR(MATCH(TEXT($B$10,"yyyymmdd")&"|"&$E$10&"|1",'EVENT ASSIGNMENT'!$K$2:$K$101,0),"")),"")) -> 29393 | D18: =IF(OR(IFERROR(MATCH(TEXT($B$10,"yyyymmdd")&"|"&$E$10&"|1",'EVENT ASSIGNMENT'!$K$2:$K$101,0),"")="",B18=""),"",IFERROR(INDEX('CONTRACT CALC'!$I$13:$I$112,IFERROR(MATCH(TEXT($B$10,"yyyymmdd")&"|"&$E$10&"|1",'EVENT ASSIGNMENT'!$K$2:$K$101,0),""))*INDEX('CONTRACT CALC'!$F$13:$F$112,IFERROR(MATCH(TEXT($B$10,"yyyymmdd")&"|"&$E$10&"|1",'EVENT ASSIGNMENT'!$K$2:$K$101,0),"")),"")) -> 22292 | E18: =IF(D18="","",D18*'CONTRACT CALC'!$B$4) -> 2229.2 | F18: =IF(OR(IFERROR(MATCH(TEXT($B$10,"yyyymmdd")&"|"&$E$10&"|1",'EVENT ASSIGNMENT'!$K$2:$K$101,0),"")="",B18=""),"",IFERROR(INDEX('CONTRACT CALC'!$H$13:$H$112,IFERROR(MATCH(TEXT($B$10,"yyyymmdd")&"|"&$E$10&"|1",'EVENT ASSIGNMENT'!$K$2:$K$101,0),""))*INDEX('CONTRACT CALC'!$F$13:$F$112,IFERROR(MATCH(TEXT($B$10,"yyyymmdd")&"|"&$E$10&"|1",'EVENT ASSIGNMENT'!$K$2:$K$101,0),"")),"")) -> 7101 | G18: =IF(F18="","",F18*'CONTRACT CALC'!$B$5) -> 568.08 | H18: =IF(B18="","",N(E18)+N(G18)) -> 2797.28 | I18: =IF(OR(IFERROR(MATCH(TEXT($B$10,"yyyymmdd")&"|"&$E$10&"|1",'EVENT ASSIGNMENT'!$K$2:$K$101,0),"")="",B18=""),"",IF(COUNTIFS('TIPS DATA'!$A$2:$A$101,$B$10,'TIPS DATA'!$C$2:$C$101,$E$10,'TIPS DATA'!$D$2:$D$101,INDEX('EVENT ASSIGNMENT'!$C$2:$C$101,IFERROR(MATCH(TEXT($B$10,"yyyymmdd")&"|"&$E$10&"|1",'EVENT ASSIGNMENT'!$K$2:$K$101,0),"")))>0,SUMIFS('TIPS DATA'!$H$2:$H$101,'TIPS DATA'!$A$2:$A$101,$B$10,'TIPS DATA'!$C$2:$C$101,$E$10,'TIPS DATA'!$D$2:$D$101,INDEX('EVENT ASSIGNMENT'!$C$2:$C$101,IFERROR(MATCH(TEXT($B$10,"yyyymmdd")&"|"&$E$10&"|1",'EVENT ASSIGNMENT'!$K$2:$K$101,0),""))),SUMIFS('TIPS DATA'!$H$2:$H$101,'TIPS DATA'!$A$2:$A$101,$B$10,'TIPS DATA'!$C$2:$C$101,$E$10,'TIPS DATA'!$E$2:$E$101,INDEX('EVENT ASSIGNMENT'!$D$2:$D$101,IFERROR(MATCH(TEXT($B$10,"yyyymmdd")&"|"&$E$10&"|1",'EVENT ASSIGNMENT'!$K$2:$K$101,0),""))))) -> 1905.76
A19: =IFERROR(MATCH(TEXT($B$10,"yyyymmdd")&"|"&$E$10&"|2",'EVENT ASSIGNMENT'!$K$2:$K$101,0),"") -> 2 | B19: =IF(IFERROR(MATCH(TEXT($B$10,"yyyymmdd")&"|"&$E$10&"|2",'EVENT ASSIGNMENT'!$K$2:$K$101,0),"")="","",IFERROR(INDEX('EVENT ASSIGNMENT'!$D$2:$D$101,IFERROR(MATCH(TEXT($B$10,"yyyymmdd")&"|"&$E$10&"|2",'EVENT ASSIGNMENT'!$K$2:$K$101,0),"")),"")) -> MBP MINI MELTS (NW) | C19: =IF(OR(IFERROR(MATCH(TEXT($B$10,"yyyymmdd")&"|"&$E$10&"|2",'EVENT ASSIGNMENT'!$K$2:$K$101,0),"")="",B19=""),"",IFERROR(INDEX('CONTRACT CALC'!$G$13:$G$112,IFERROR(MATCH(TEXT($B$10,"yyyymmdd")&"|"&$E$10&"|2",'EVENT ASSIGNMENT'!$K$2:$K$101,0),""))*INDEX('CONTRACT CALC'!$F$13:$F$112,IFERROR(MATCH(TEXT($B$10,"yyyymmdd")&"|"&$E$10&"|2",'EVENT ASSIGNMENT'!$K$2:$K$101,0),"")),"")) -> 1930 | D19: =IF(OR(IFERROR(MATCH(TEXT($B$10,"yyyymmdd")&"|"&$E$10&"|2",'EVENT ASSIGNMENT'!$K$2:$K$101,0),"")="",B19=""),"",IFERROR(INDEX('CONTRACT CALC'!$I$13:$I$112,IFERROR(MATCH(TEXT($B$10,"yyyymmdd")&"|"&$E$10&"|2",'EVENT ASSIGNMENT'!$K$2:$K$101,0),""))*INDEX('CONTRACT CALC'!$F$13:$F$112,IFERROR(MATCH(TEXT($B$10,"yyyymmdd")&"|"&$E$10&"|2",'EVENT ASSIGNMENT'!$K$2:$K$101,0),"")),"")) -> 1930 | E19: =IF(D19="","",D19*'CONTRACT CALC'!$B$4) -> 193 | F19: =IF(OR(IFERROR(MATCH(TEXT($B$10,"yyyymmdd")&"|"&$E$10&"|2",'EVENT ASSIGNMENT'!$K$2:$K$101,0),"")="",B19=""),"",IFERROR(INDEX('CONTRACT CALC'!$H$13:$H$112,IFERROR(MATCH(TEXT($B$10,"yyyymmdd")&"|"&$E$10&"|2",'EVENT ASSIGNMENT'!$K$2:$K$101,0),""))*INDEX('CONTRACT CALC'!$F$13:$F$112,IFERROR(MATCH(TEXT($B$10,"yyyymmdd")&"|"&$E$10&"|2",'EVENT ASSIGNMENT'!$K$2:$K$101,0),"")),"")) -> 0 | G19: =IF(F19="","",F19*'CONTRACT CALC'!$B$5) -> 0 | H19: =IF(B19="","",N(E19)+N(G19)) -> 193 | I19: =IF(OR(IFERROR(MATCH(TEXT($B$10,"yyyymmdd")&"|"&$E$10&"|2",'EVENT ASSIGNMENT'!$K$2:$K$101,0),"")="",B19=""),"",IF(COUNTIFS('TIPS DATA'!$A$2:$A$101,$B$10,'TIPS DATA'!$C$2:$C$101,$E$10,'TIPS DATA'!$D$2:$D$101,INDEX('EVENT ASSIGNMENT'!$C$2:$C$101,IFERROR(MATCH(TEXT($B$10,"yyyymmdd")&"|"&$E$10&"|2",'EVENT ASSIGNMENT'!$K$2:$K$101,0),"")))>0,SUMIFS('TIPS DATA'!$H$2:$H$101,'TIPS DATA'!$A$2:$A$101,$B$10,'TIPS DATA'!$C$2:$C$101,$E$10,'TIPS DATA'!$D$2:$D$101,INDEX('EVENT ASSIGNMENT'!$C$2:$C$101,IFERROR(MATCH(TEXT($B$10,"yyyymmdd")&"|"&$E$10&"|2",'EVENT ASSIGNMENT'!$K$2:$K$101,0),""))),SUMIFS('TIPS DATA'!$H$2:$H$101,'TIPS DATA'!$A$2:$A$101,$B$10,'TIPS DATA'!$C$2:$C$101,$E$10,'TIPS DATA'!$E$2:$E$101,INDEX('EVENT ASSIGNMENT'!$D$2:$D$101,IFERROR(MATCH(TEXT($B$10,"yyyymmdd")&"|"&$E$10&"|2",'EVENT ASSIGNMENT'!$K$2:$K$101,0),""))))) -> 154.32
A20: =IFERROR(MATCH(TEXT($B$10,"yyyymmdd")&"|"&$E$10&"|3",'EVENT ASSIGNMENT'!$K$2:$K$101,0),"") -> 3 | B20: =IF(IFERROR(MATCH(TEXT($B$10,"yyyymmdd")&"|"&$E$10&"|3",'EVENT ASSIGNMENT'!$K$2:$K$101,0),"")="","",IFERROR(INDEX('EVENT ASSIGNMENT'!$D$2:$D$101,IFERROR(MATCH(TEXT($B$10,"yyyymmdd")&"|"&$E$10&"|3",'EVENT ASSIGNMENT'!$K$2:$K$101,0),"")),"")) -> MBP MINI MELTS (NE) | C20: =IF(OR(IFERROR(MATCH(TEXT($B$10,"yyyymmdd")&"|"&$E$10&"|3",'EVENT ASSIGNMENT'!$K$2:$K$101,0),"")="",B20=""),"",IFERROR(INDEX('CONTRACT CALC'!$G$13:$G$112,IFERROR(MATCH(TEXT($B$10,"yyyymmdd")&"|"&$E$10&"|3",'EVENT ASSIGNMENT'!$K$2:$K$101,0),""))*INDEX('CONTRACT CALC'!$F$13:$F$112,IFERROR(MATCH(TEXT($B$10,"yyyymmdd")&"|"&$E$10&"|3",'EVENT ASSIGNMENT'!$K$2:$K$101,0),"")),"")) -> 2330 | D20: =IF(OR(IFERROR(MATCH(TEXT($B$10,"yyyymmdd")&"|"&$E$10&"|3",'EVENT ASSIGNMENT'!$K$2:$K$101,0),"")="",B20=""),"",IFERROR(INDEX('CONTRACT CALC'!$I$13:$I$112,IFERROR(MATCH(TEXT($B$10,"yyyymmdd")&"|"&$E$10&"|3",'EVENT ASSIGNMENT'!$K$2:$K$101,0),""))*INDEX('CONTRACT CALC'!$F$13:$F$112,IFERROR(MATCH(TEXT($B$10,"yyyymmdd")&"|"&$E$10&"|3",'EVENT ASSIGNMENT'!$K$2:$K$101,0),"")),"")) -> 2330 | E20: =IF(D20="","",D20*'CONTRACT CALC'!$B$4) -> 233 | F20: =IF(OR(IFERROR(MATCH(TEXT($B$10,"yyyymmdd")&"|"&$E$10&"|3",'EVENT ASSIGNMENT'!$K$2:$K$101,0),"")="",B20=""),"",IFERROR(INDEX('CONTRACT CALC'!$H$13:$H$112,IFERROR(MATCH(TEXT($B$10,"yyyymmdd")&"|"&$E$10&"|3",'EVENT ASSIGNMENT'!$K$2:$K$101,0),""))*INDEX('CONTRACT CALC'!$F$13:$F$112,IFERROR(MATCH(TEXT($B$10,"yyyymmdd")&"|"&$E$10&"|3",'EVENT ASSIGNMENT'!$K$2:$K$101,0),"")),"")) -> 0 | G20: =IF(F20="","",F20*'CONTRACT CALC'!$B$5) -> 0 | H20: =IF(B20="","",N(E20)+N(G20)) -> 233 | I20: =IF(OR(IFERROR(MATCH(TEXT($B$10,"yyyymmdd")&"|"&$E$10&"|3",'EVENT ASSIGNMENT'!$K$2:$K$101,0),"")="",B20=""),"",IF(COUNTIFS('TIPS DATA'!$A$2:$A$101,$B$10,'TIPS DATA'!$C$2:$C$101,$E$10,'TIPS DATA'!$D$2:$D$101,INDEX('EVENT ASSIGNMENT'!$C$2:$C$101,IFERROR(MATCH(TEXT($B$10,"yyyymmdd")&"|"&$E$10&"|3",'EVENT ASSIGNMENT'!$K$2:$K$101,0),"")))>0,SUMIFS('TIPS DATA'!$H$2:$H$101,'TIPS DATA'!$A$2:$A$101,$B$10,'TIPS DATA'!$C$2:$C$101,$E$10,'TIPS DATA'!$D$2:$D$101,INDEX('EVENT ASSIGNMENT'!$C$2:$C$101,IFERROR(MATCH(TEXT($B$10,"yyyymmdd")&"|"&$E$10&"|3",'EVENT ASSIGNMENT'!$K$2:$K$101,0),""))),SUMIFS('TIPS DATA'!$H$2:$H$101,'TIPS DATA'!$A$2:$A$101,$B$10,'TIPS DATA'!$C$2:$C$101,$E$10,'TIPS DATA'!$E$2:$E$101,INDEX('EVENT ASSIGNMENT'!$D$2:$D$101,IFERROR(MATCH(TEXT($B$10,"yyyymmdd")&"|"&$E$10&"|3",'EVENT ASSIGNMENT'!$K$2:$K$101,0),""))))) -> 189
A21: =IFERROR(MATCH(TEXT($B$10,"yyyymmdd")&"|"&$E$10&"|4",'EVENT ASSIGNMENT'!$K$2:$K$101,0),"") -> 4 | B21: =IF(IFERROR(MATCH(TEXT($B$10,"yyyymmdd")&"|"&$E$10&"|4",'EVENT ASSIGNMENT'!$K$2:$K$101,0),"")="","",IFERROR(INDEX('EVENT ASSIGNMENT'!$D$2:$D$101,IFERROR(MATCH(TEXT($B$10,"yyyymmdd")&"|"&$E$10&"|4",'EVENT ASSIGNMENT'!$K$2:$K$101,0),"")),"")) -> MBP TRAILER N CONCOURSE | C21: =IF(OR(IFERROR(MATCH(TEXT($B$10,"yyyymmdd")&"|"&$E$10&"|4",'EVENT ASSIGNMENT'!$K$2:$K$101,0),"")="",B21=""),"",IFERROR(INDEX('CONTRACT CALC'!$G$13:$G$112,IFERROR(MATCH(TEXT($B$10,"yyyymmdd")&"|"&$E$10&"|4",'EVENT ASSIGNMENT'!$K$2:$K$101,0),""))*INDEX('CONTRACT CALC'!$F$13:$F$112,IFERROR(MATCH(TEXT($B$10,"yyyymmdd")&"|"&$E$10&"|4",'EVENT ASSIGNMENT'!$K$2:$K$101,0),"")),"")) -> 7626 | D21: =IF(OR(IFERROR(MATCH(TEXT($B$10,"yyyymmdd")&"|"&$E$10&"|4",'EVENT ASSIGNMENT'!$K$2:$K$101,0),"")="",B21=""),"",IFERROR(INDEX('CONTRACT CALC'!$I$13:$I$112,IFERROR(MATCH(TEXT($B$10,"yyyymmdd")&"|"&$E$10&"|4",'EVENT ASSIGNMENT'!$K$2:$K$101,0),""))*INDEX('CONTRACT CALC'!$F$13:$F$112,IFERROR(MATCH(TEXT($B$10,"yyyymmdd")&"|"&$E$10&"|4",'EVENT ASSIGNMENT'!$K$2:$K$101,0),"")),"")) -> 688 | E21: =IF(D21="","",D21*'CONTRACT CALC'!$B$4) -> 68.8 | F21: =IF(OR(IFERROR(MATCH(TEXT($B$10,"yyyymmdd")&"|"&$E$10&"|4",'EVENT ASSIGNMENT'!$K$2:$K$101,0),"")="",B21=""),"",IFERROR(INDEX('CONTRACT CALC'!$H$13:$H$112,IFERROR(MATCH(TEXT($B$10,"yyyymmdd")&"|"&$E$10&"|4",'EVENT ASSIGNMENT'!$K$2:$K$101,0),""))*INDEX('CONTRACT CALC'!$F$13:$F$112,IFERROR(MATCH(TEXT($B$10,"yyyymmdd")&"|"&$E$10&"|4",'EVENT ASSIGNMENT'!$K$2:$K$101,0),"")),"")) -> 6938 | G21: =IF(F21="","",F21*'CONTRACT CALC'!$B$5) -> 555.04 | H21: =IF(B21="","",N(E21)+N(G21)) -> 623.84 | I21: =IF(OR(IFERROR(MATCH(TEXT($B$10,"yyyymmdd")&"|"&$E$10&"|4",'EVENT ASSIGNMENT'!$K$2:$K$101,0),"")="",B21=""),"",IF(COUNTIFS('TIPS DATA'!$A$2:$A$101,$B$10,'TIPS DATA'!$C$2:$C$101,$E$10,'TIPS DATA'!$D$2:$D$101,INDEX('EVENT ASSIGNMENT'!$C$2:$C$101,IFERROR(MATCH(TEXT($B$10,"yyyymmdd")&"|"&$E$10&"|4",'EVENT ASSIGNMENT'!$K$2:$K$101,0),"")))>0,SUMIFS('TIPS DATA'!$H$2:$H$101,'TIPS DATA'!$A$2:$A$101,$B$10,'TIPS DATA'!$C$2:$C$101,$E$10,'TIPS DATA'!$D$2:$D$101,INDEX('EVENT ASSIGNMENT'!$C$2:$C$101,IFERROR(MATCH(TEXT($B$10,"yyyymmdd")&"|"&$E$10&"|4",'EVENT ASSIGNMENT'!$K$2:$K$101,0),""))),SUMIFS('TIPS DATA'!$H$2:$H$101,'TIPS DATA'!$A$2:$A$101,$B$10,'TIPS DATA'!$C$2:$C$101,$E$10,'TIPS DATA'!$E$2:$E$101,INDEX('EVENT ASSIGNMENT'!$D$2:$D$101,IFERROR(MATCH(TEXT($B$10,"yyyymmdd")&"|"&$E$10&"|4",'EVENT ASSIGNMENT'!$K$2:$K$101,0),""))))) -> 670.54
A22: =IFERROR(MATCH(TEXT($B$10,"yyyymmdd")&"|"&$E$10&"|5",'EVENT ASSIGNMENT'!$K$2:$K$101,0),"") -> 5 | B22: =IF(IFERROR(MATCH(TEXT($B$10,"yyyymmdd")&"|"&$E$10&"|5",'EVENT ASSIGNMENT'!$K$2:$K$101,0),"")="","",IFERROR(INDEX('EVENT ASSIGNMENT'!$D$2:$D$101,IFERROR(MATCH(TEXT($B$10,"yyyymmdd")&"|"&$E$10&"|5",'EVENT ASSIGNMENT'!$K$2:$K$101,0),"")),"")) -> NE SPECIALTY DAWG O.G. | C22: =IF(OR(IFERROR(MATCH(TEXT($B$10,"yyyymmdd")&"|"&$E$10&"|5",'EVENT ASSIGNMENT'!$K$2:$K$101,0),"")="",B22=""),"",IFERROR(INDEX('CONTRACT CALC'!$G$13:$G$112,IFERROR(MATCH(TEXT($B$10,"yyyymmdd")&"|"&$E$10&"|5",'EVENT ASSIGNMENT'!$K$2:$K$101,0),""))*INDEX('CONTRACT CALC'!$F$13:$F$112,IFERROR(MATCH(TEXT($B$10,"yyyymmdd")&"|"&$E$10&"|5",'EVENT ASSIGNMENT'!$K$2:$K$101,0),"")),"")) -> 6745 | D22: =IF(OR(IFERROR(MATCH(TEXT($B$10,"yyyymmdd")&"|"&$E$10&"|5",'EVENT ASSIGNMENT'!$K$2:$K$101,0),"")="",B22=""),"",IFERROR(INDEX('CONTRACT CALC'!$I$13:$I$112,IFERROR(MATCH(TEXT($B$10,"yyyymmdd")&"|"&$E$10&"|5",'EVENT ASSIGNMENT'!$K$2:$K$101,0),""))*INDEX('CONTRACT CALC'!$F$13:$F$112,IFERROR(MATCH(TEXT($B$10,"yyyymmdd")&"|"&$E$10&"|5",'EVENT ASSIGNMENT'!$K$2:$K$101,0),"")),"")) -> 5005 | E22: =IF(D22="","",D22*'CONTRACT CALC'!$B$4) -> 500.5 | F22: =IF(OR(IFERROR(MATCH(TEXT($B$10,"yyyymmdd")&"|"&$E$10&"|5",'EVENT ASSIGNMENT'!$K$2:$K$101,0),"")="",B22=""),"",IFERROR(INDEX('CONTRACT CALC'!$H$13:$H$112,IFERROR(MATCH(TEXT($B$10,"yyyymmdd")&"|"&$E$10&"|5",'EVENT ASSIGNMENT'!$K$2:$K$101,0),""))*INDEX('CONTRACT CALC'!$F$13:$F$112,IFERROR(MATCH(TEXT($B$10,"yyyymmdd")&"|"&$E$10&"|5",'EVENT ASSIGNMENT'!$K$2:$K$101,0),"")),"")) -> 1740 | G22: =IF(F22="","",F22*'CONTRACT CALC'!$B$5) -> 139.2 | H22: =IF(B22="","",N(E22)+N(G22)) -> 639.7 | I22: =IF(OR(IFERROR(MATCH(TEXT($B$10,"yyyymmdd")&"|"&$E$10&"|5",'EVENT ASSIGNMENT'!$K$2:$K$101,0),"")="",B22=""),"",IF(COUNTIFS('TIPS DATA'!$A$2:$A$101,$B$10,'TIPS DATA'!$C$2:$C$101,$E$10,'TIPS DATA'!$D$2:$D$101,INDEX('EVENT ASSIGNMENT'!$C$2:$C$101,IFERROR(MATCH(TEXT($B$10,"yyyymmdd")&"|"&$E$10&"|5",'EVENT ASSIGNMENT'!$K$2:$K$101,0),"")))>0,SUMIFS('TIPS DATA'!$H$2:$H$101,'TIPS DATA'!$A$2:$A$101,$B$10,'TIPS DATA'!$C$2:$C$101,$E$10,'TIPS DATA'!$D$2:$D$101,INDEX('EVENT ASSIGNMENT'!$C$2:$C$101,IFERROR(MATCH(TEXT($B$10,"yyyymmdd")&"|"&$E$10&"|5",'EVENT ASSIGNMENT'!$K$2:$K$101,0),""))),SUMIFS('TIPS DATA'!$H$2:$H$101,'TIPS DATA'!$A$2:$A$101,$B$10,'TIPS DATA'!$C$2:$C$101,$E$10,'TIPS DATA'!$E$2:$E$101,INDEX('EVENT ASSIGNMENT'!$D$2:$D$101,IFERROR(MATCH(TEXT($B$10,"yyyymmdd")&"|"&$E$10&"|5",'EVENT ASSIGNMENT'!$K$2:$K$101,0),""))))) -> 502.12
A23: =IFERROR(MATCH(TEXT($B$10,"yyyymmdd")&"|"&$E$10&"|6",'EVENT ASSIGNMENT'!$K$2:$K$101,0),"") | B23: =IF(IFERROR(MATCH(TEXT($B$10,"yyyymmdd")&"|"&$E$10&"|6",'EVENT ASSIGNMENT'!$K$2:$K$101,0),"")="","",IFERROR(INDEX('EVENT ASSIGNMENT'!$D$2:$D$101,IFERROR(MATCH(TEXT($B$10,"yyyymmdd")&"|"&$E$10&"|6",'EVENT ASSIGNMENT'!$K$2:$K$101,0),"")),"")) | C23: =IF(OR(IFERROR(MATCH(TEXT($B$10,"yyyymmdd")&"|"&$E$10&"|6",'EVENT ASSIGNMENT'!$K$2:$K$101,0),"")="",B23=""),"",IFERROR(INDEX('CONTRACT CALC'!$G$13:$G$112,IFERROR(MATCH(TEXT($B$10,"yyyymmdd")&"|"&$E$10&"|6",'EVENT ASSIGNMENT'!$K$2:$K$101,0),""))*INDEX('CONTRACT CALC'!$F$13:$F$112,IFERROR(MATCH(TEXT($B$10,"yyyymmdd")&"|"&$E$10&"|6",'EVENT ASSIGNMENT'!$K$2:$K$101,0),"")),"")) | D23: =IF(OR(IFERROR(MATCH(TEXT($B$10,"yyyymmdd")&"|"&$E$10&"|6",'EVENT ASSIGNMENT'!$K$2:$K$101,0),"")="",B23=""),"",IFERROR(INDEX('CONTRACT CALC'!$I$13:$I$112,IFERROR(MATCH(TEXT($B$10,"yyyymmdd")&"|"&$E$10&"|6",'EVENT ASSIGNMENT'!$K$2:$K$101,0),""))*INDEX('CONTRACT CALC'!$F$13:$F$112,IFERROR(MATCH(TEXT($B$10,"yyyymmdd")&"|"&$E$10&"|6",'EVENT ASSIGNMENT'!$K$2:$K$101,0),"")),"")) | E23: =IF(D23="","",D23*'CONTRACT CALC'!$B$4) | F23: =IF(OR(IFERROR(MATCH(TEXT($B$10,"yyyymmdd")&"|"&$E$10&"|6",'EVENT ASSIGNMENT'!$K$2:$K$101,0),"")="",B23=""),"",IFERROR(INDEX('CONTRACT CALC'!$H$13:$H$112,IFERROR(MATCH(TEXT($B$10,"yyyymmdd")&"|"&$E$10&"|6",'EVENT ASSIGNMENT'!$K$2:$K$101,0),""))*INDEX('CONTRACT CALC'!$F$13:$F$112,IFERROR(MATCH(TEXT($B$10,"yyyymmdd")&"|"&$E$10&"|6",'EVENT ASSIGNMENT'!$K$2:$K$101,0),"")),"")) | G23: =IF(F23="","",F23*'CONTRACT CALC'!$B$5) | H23: =IF(B23="","",N(E23)+N(G23)) | I23: =IF(OR(IFERROR(MATCH(TEXT($B$10,"yyyymmdd")&"|"&$E$10&"|6",'EVENT ASSIGNMENT'!$K$2:$K$101,0),"")="",B23=""),"",IF(COUNTIFS('TIPS DATA'!$A$2:$A$101,$B$10,'TIPS DATA'!$C$2:$C$101,$E$10,'TIPS DATA'!$D$2:$D$101,INDEX('EVENT ASSIGNMENT'!$C$2:$C$101,IFERROR(MATCH(TEXT($B$10,"yyyymmdd")&"|"&$E$10&"|6",'EVENT ASSIGNMENT'!$K$2:$K$101,0),"")))>0,SUMIFS('TIPS DATA'!$H$2:$H$101,'TIPS DATA'!$A$2:$A$101,$B$10,'TIPS DATA'!$C$2:$C$101,$E$10,'TIPS DATA'!$D$2:$D$101,INDEX('EVENT ASSIGNMENT'!$C$2:$C$101,IFERROR(MATCH(TEXT($B$10,"yyyymmdd")&"|"&$E$10&"|6",'EVENT ASSIGNMENT'!$K$2:$K$101,0),""))),SUMIFS('TIPS DATA'!$H$2:$H$101,'TIPS DATA'!$A$2:$A$101,$B$10,'TIPS DATA'!$C$2:$C$101,$E$10,'TIPS DATA'!$E$2:$E$101,INDEX('EVENT ASSIGNMENT'!$D$2:$D$101,IFERROR(MATCH(TEXT($B$10,"yyyymmdd")&"|"&$E$10&"|6",'EVENT ASSIGNMENT'!$K$2:$K$101,0),"")))))
A24: =IFERROR(MATCH(TEXT($B$10,"yyyymmdd")&"|"&$E$10&"|7",'EVENT ASSIGNMENT'!$K$2:$K$101,0),"") | B24: =IF(IFERROR(MATCH(TEXT($B$10,"yyyymmdd")&"|"&$E$10&"|7",'EVENT ASSIGNMENT'!$K$2:$K$101,0),"")="","",IFERROR(INDEX('EVENT ASSIGNMENT'!$D$2:$D$101,IFERROR(MATCH(TEXT($B$10,"yyyymmdd")&"|"&$E$10&"|7",'EVENT ASSIGNMENT'!$K$2:$K$101,0),"")),"")) | C24: =IF(OR(IFERROR(MATCH(TEXT($B$10,"yyyymmdd")&"|"&$E$10&"|7",'EVENT ASSIGNMENT'!$K$2:$K$101,0),"")="",B24=""),"",IFERROR(INDEX('CONTRACT CALC'!$G$13:$G$112,IFERROR(MATCH(TEXT($B$10,"yyyymmdd")&"|"&$E$10&"|7",'EVENT ASSIGNMENT'!$K$2:$K$101,0),""))*INDEX('CONTRACT CALC'!$F$13:$F$112,IFERROR(MATCH(TEXT($B$10,"yyyymmdd")&"|"&$E$10&"|7",'EVENT ASSIGNMENT'!$K$2:$K$101,0),"")),"")) | D24: =IF(OR(IFERROR(MATCH(TEXT($B$10,"yyyymmdd")&"|"&$E$10&"|7",'EVENT ASSIGNMENT'!$K$2:$K$101,0),"")="",B24=""),"",IFERROR(INDEX('CONTRACT CALC'!$I$13:$I$112,IFERROR(MATCH(TEXT($B$10,"yyyymmdd")&"|"&$E$10&"|7",'EVENT ASSIGNMENT'!$K$2:$K$101,0),""))*INDEX('CONTRACT CALC'!$F$13:$F$112,IFERROR(MATCH(TEXT($B$10,"yyyymmdd")&"|"&$E$10&"|7",'EVENT ASSIGNMENT'!$K$2:$K$101,0),"")),"")) | E24: =IF(D24="","",D24*'CONTRACT CALC'!$B$4) | F24: =IF(OR(IFERROR(MATCH(TEXT($B$10,"yyyymmdd")&"|"&$E$10&"|7",'EVENT ASSIGNMENT'!$K$2:$K$101,0),"")="",B24=""),"",IFERROR(INDEX('CONTRACT CALC'!$H$13:$H$112,IFERROR(MATCH(TEXT($B$10,"yyyymmdd")&"|"&$E$10&"|7",'EVENT ASSIGNMENT'!$K$2:$K$101,0),""))*INDEX('CONTRACT CALC'!$F$13:$F$112,IFERROR(MATCH(TEXT($B$10,"yyyymmdd")&"|"&$E$10&"|7",'EVENT ASSIGNMENT'!$K$2:$K$101,0),"")),"")) | G24: =IF(F24="","",F24*'CONTRACT CALC'!$B$5) | H24: =IF(B24="","",N(E24)+N(G24)) | I24: =IF(OR(IFERROR(MATCH(TEXT($B$10,"yyyymmdd")&"|"&$E$10&"|7",'EVENT ASSIGNMENT'!$K$2:$K$101,0),"")="",B24=""),"",IF(COUNTIFS('TIPS DATA'!$A$2:$A$101,$B$10,'TIPS DATA'!$C$2:$C$101,$E$10,'TIPS DATA'!$D$2:$D$101,INDEX('EVENT ASSIGNMENT'!$C$2:$C$101,IFERROR(MATCH(TEXT($B$10,"yyyymmdd")&"|"&$E$10&"|7",'EVENT ASSIGNMENT'!$K$2:$K$101,0),"")))>0,SUMIFS('TIPS DATA'!$H$2:$H$101,'TIPS DATA'!$A$2:$A$101,$B$10,'TIPS DATA'!$C$2:$C$101,$E$10,'TIPS DATA'!$D$2:$D$101,INDEX('EVENT ASSIGNMENT'!$C$2:$C$101,IFERROR(MATCH(TEXT($B$10,"yyyymmdd")&"|"&$E$10&"|7",'EVENT ASSIGNMENT'!$K$2:$K$101,0),""))),SUMIFS('TIPS DATA'!$H$2:$H$101,'TIPS DATA'!$A$2:$A$101,$B$10,'TIPS DATA'!$C$2:$C$101,$E$10,'TIPS DATA'!$E$2:$E$101,INDEX('EVENT ASSIGNMENT'!$D$2:$D$101,IFERROR(MATCH(TEXT($B$10,"yyyymmdd")&"|"&$E$10&"|7",'EVENT ASSIGNMENT'!$K$2:$K$101,0),"")))))
A25: =IFERROR(MATCH(TEXT($B$10,"yyyymmdd")&"|"&$E$10&"|8",'EVENT ASSIGNMENT'!$K$2:$K$101,0),"") | B25: =IF(IFERROR(MATCH(TEXT($B$10,"yyyymmdd")&"|"&$E$10&"|8",'EVENT ASSIGNMENT'!$K$2:$K$101,0),"")="","",IFERROR(INDEX('EVENT ASSIGNMENT'!$D$2:$D$101,IFERROR(MATCH(TEXT($B$10,"yyyymmdd")&"|"&$E$10&"|8",'EVENT ASSIGNMENT'!$K$2:$K$101,0),"")),"")) | C25: =IF(OR(IFERROR(MATCH(TEXT($B$10,"yyyymmdd")&"|"&$E$10&"|8",'EVENT ASSIGNMENT'!$K$2:$K$101,0),"")="",B25=""),"",IFERROR(INDEX('CONTRACT CALC'!$G$13:$G$112,IFERROR(MATCH(TEXT($B$10,"yyyymmdd")&"|"&$E$10&"|8",'EVENT ASSIGNMENT'!$K$2:$K$101,0),""))*INDEX('CONTRACT CALC'!$F$13:$F$112,IFERROR(MATCH(TEXT($B$10,"yyyymmdd")&"|"&$E$10&"|8",'EVENT ASSIGNMENT'!$K$2:$K$101,0),"")),"")) | D25: =IF(OR(IFERROR(MATCH(TEXT($B$10,"yyyymmdd")&"|"&$E$10&"|8",'EVENT ASSIGNMENT'!$K$2:$K$101,0),"")="",B25=""),"",IFERROR(INDEX('CONTRACT CALC'!$I$13:$I$112,IFERROR(MATCH(TEXT($B$10,"yyyymmdd")&"|"&$E$10&"|8",'EVENT ASSIGNMENT'!$K$2:$K$101,0),""))*INDEX('CONTRACT CALC'!$F$13:$F$112,IFERROR(MATCH(TEXT($B$10,"yyyymmdd")&"|"&$E$10&"|8",'EVENT ASSIGNMENT'!$K$2:$K$101,0),"")),"")) | E25: =IF(D25="","",D25*'CONTRACT CALC'!$B$4) | F25: =IF(OR(IFERROR(MATCH(TEXT($B$10,"yyyymmdd")&"|"&$E$10&"|8",'EVENT ASSIGNMENT'!$K$2:$K$101,0),"")="",B25=""),"",IFERROR(INDEX('CONTRACT CALC'!$H$13:$H$112,IFERROR(MATCH(TEXT($B$10,"yyyymmdd")&"|"&$E$10&"|8",'EVENT ASSIGNMENT'!$K$2:$K$101,0),""))*INDEX('CONTRACT CALC'!$F$13:$F$112,IFERROR(MATCH(TEXT($B$10,"yyyymmdd")&"|"&$E$10&"|8",'EVENT ASSIGNMENT'!$K$2:$K$101,0),"")),"")) | G25: =IF(F25="","",F25*'CONTRACT CALC'!$B$5) | H25: =IF(B25="","",N(E25)+N(G25)) | I25: =IF(OR(IFERROR(MATCH(TEXT($B$10,"yyyymmdd")&"|"&$E$10&"|8",'EVENT ASSIGNMENT'!$K$2:$K$101,0),"")="",B25=""),"",IF(COUNTIFS('TIPS DATA'!$A$2:$A$101,$B$10,'TIPS DATA'!$C$2:$C$101,$E$10,'TIPS DATA'!$D$2:$D$101,INDEX('EVENT ASSIGNMENT'!$C$2:$C$101,IFERROR(MATCH(TEXT($B$10,"yyyymmdd")&"|"&$E$10&"|8",'EVENT ASSIGNMENT'!$K$2:$K$101,0),"")))>0,SUMIFS('TIPS DATA'!$H$2:$H$101,'TIPS DATA'!$A$2:$A$101,$B$10,'TIPS DATA'!$C$2:$C$101,$E$10,'TIPS DATA'!$D$2:$D$101,INDEX('EVENT ASSIGNMENT'!$C$2:$C$101,IFERROR(MATCH(TEXT($B$10,"yyyymmdd")&"|"&$E$10&"|8",'EVENT ASSIGNMENT'!$K$2:$K$101,0),""))),SUMIFS('TIPS DATA'!$H$2:$H$101,'TIPS DATA'!$A$2:$A$101,$B$10,'TIPS DATA'!$C$2:$C$101,$E$10,'TIPS DATA'!$E$2:$E$101,INDEX('EVENT ASSIGNMENT'!$D$2:$D$101,IFERROR(MATCH(TEXT($B$10,"yyyymmdd")&"|"&$E$10&"|8",'EVENT ASSIGNMENT'!$K$2:$K$101,0),"")))))
A26: =IFERROR(MATCH(TEXT($B$10,"yyyymmdd")&"|"&$E$10&"|9",'EVENT ASSIGNMENT'!$K$2:$K$101,0),"") | B26: =IF(IFERROR(MATCH(TEXT($B$10,"yyyymmdd")&"|"&$E$10&"|9",'EVENT ASSIGNMENT'!$K$2:$K$101,0),"")="","",IFERROR(INDEX('EVENT ASSIGNMENT'!$D$2:$D$101,IFERROR(MATCH(TEXT($B$10,"yyyymmdd")&"|"&$E$10&"|9",'EVENT ASSIGNMENT'!$K$2:$K$101,0),"")),"")) | C26: =IF(OR(IFERROR(MATCH(TEXT($B$10,"yyyymmdd")&"|"&$E$10&"|9",'EVENT ASSIGNMENT'!$K$2:$K$101,0),"")="",B26=""),"",IFERROR(INDEX('CONTRACT CALC'!$G$13:$G$112,IFERROR(MATCH(TEXT($B$10,"yyyymmdd")&"|"&$E$10&"|9",'EVENT ASSIGNMENT'!$K$2:$K$101,0),""))*INDEX('CONTRACT CALC'!$F$13:$F$112,IFERROR(MATCH(TEXT($B$10,"yyyymmdd")&"|"&$E$10&"|9",'EVENT ASSIGNMENT'!$K$2:$K$101,0),"")),"")) | D26: =IF(OR(IFERROR(MATCH(TEXT($B$10,"yyyymmdd")&"|"&$E$10&"|9",'EVENT ASSIGNMENT'!$K$2:$K$101,0),"")="",B26=""),"",IFERROR(INDEX('CONTRACT CALC'!$I$13:$I$112,IFERROR(MATCH(TEXT($B$10,"yyyymmdd")&"|"&$E$10&"|9",'EVENT ASSIGNMENT'!$K$2:$K$101,0),""))*INDEX('CONTRACT CALC'!$F$13:$F$112,IFERROR(MATCH(TEXT($B$10,"yyyymmdd")&"|"&$E$10&"|9",'EVENT ASSIGNMENT'!$K$2:$K$101,0),"")),"")) | E26: =IF(D26="","",D26*'CONTRACT CALC'!$B$4) | F26: =IF(OR(IFERROR(MATCH(TEXT($B$10,"yyyymmdd")&"|"&$E$10&"|9",'EVENT ASSIGNMENT'!$K$2:$K$101,0),"")="",B26=""),"",IFERROR(INDEX('CONTRACT CALC'!$H$13:$H$112,IFERROR(MATCH(TEXT($B$10,"yyyymmdd")&"|"&$E$10&"|9",'EVENT ASSIGNMENT'!$K$2:$K$101,0),""))*INDEX('CONTRACT CALC'!$F$13:$F$112,IFERROR(MATCH(TEXT($B$10,"yyyymmdd")&"|"&$E$10&"|9",'EVENT ASSIGNMENT'!$K$2:$K$101,0),"")),"")) | G26: =IF(F26="","",F26*'CONTRACT CALC'!$B$5) | H26: =IF(B26="","",N(E26)+N(G26)) | I26: =IF(OR(IFERROR(MATCH(TEXT($B$10,"yyyymmdd")&"|"&$E$10&"|9",'EVENT ASSIGNMENT'!$K$2:$K$101,0),"")="",B26=""),"",IF(COUNTIFS('TIPS DATA'!$A$2:$A$101,$B$10,'TIPS DATA'!$C$2:$C$101,$E$10,'TIPS DATA'!$D$2:$D$101,INDEX('EVENT ASSIGNMENT'!$C$2:$C$101,IFERROR(MATCH(TEXT($B$10,"yyyymmdd")&"|"&$E$10&"|9",'EVENT ASSIGNMENT'!$K$2:$K$101,0),"")))>0,SUMIFS('TIPS DATA'!$H$2:$H$101,'TIPS DATA'!$A$2:$A$101,$B$10,'TIPS DATA'!$C$2:$C$101,$E$10,'TIPS DATA'!$D$2:$D$101,INDEX('EVENT ASSIGNMENT'!$C$2:$C$101,IFERROR(MATCH(TEXT($B$10,"yyyymmdd")&"|"&$E$10&"|9",'EVENT ASSIGNMENT'!$K$2:$K$101,0),""))),SUMIFS('TIPS DATA'!$H$2:$H$101,'TIPS DATA'!$A$2:$A$101,$B$10,'TIPS DATA'!$C$2:$C$101,$E$10,'TIPS DATA'!$E$2:$E$101,INDEX('EVENT ASSIGNMENT'!$D$2:$D$101,IFERROR(MATCH(TEXT($B$10,"yyyymmdd")&"|"&$E$10&"|9",'EVENT ASSIGNMENT'!$K$2:$K$101,0),"")))))
A27: =IFERROR(MATCH(TEXT($B$10,"yyyymmdd")&"|"&$E$10&"|10",'EVENT ASSIGNMENT'!$K$2:$K$101,0),"") | B27: =IF(IFERROR(MATCH(TEXT($B$10,"yyyymmdd")&"|"&$E$10&"|10",'EVENT ASSIGNMENT'!$K$2:$K$101,0),"")="","",IFERROR(INDEX('EVENT ASSIGNMENT'!$D$2:$D$101,IFERROR(MATCH(TEXT($B$10,"yyyymmdd")&"|"&$E$10&"|10",'EVENT ASSIGNMENT'!$K$2:$K$101,0),"")),"")) | C27: =IF(OR(IFERROR(MATCH(TEXT($B$10,"yyyymmdd")&"|"&$E$10&"|10",'EVENT ASSIGNMENT'!$K$2:$K$101,0),"")="",B27=""),"",IFERROR(INDEX('CONTRACT CALC'!$G$13:$G$112,IFERROR(MATCH(TEXT($B$10,"yyyymmdd")&"|"&$E$10&"|10",'EVENT ASSIGNMENT'!$K$2:$K$101,0),""))*INDEX('CONTRACT CALC'!$F$13:$F$112,IFERROR(MATCH(TEXT($B$10,"yyyymmdd")&"|"&$E$10&"|10",'EVENT ASSIGNMENT'!$K$2:$K$101,0),"")),"")) | D27: =IF(OR(IFERROR(MATCH(TEXT($B$10,"yyyymmdd")&"|"&$E$10&"|10",'EVENT ASSIGNMENT'!$K$2:$K$101,0),"")="",B27=""),"",IFERROR(INDEX('CONTRACT CALC'!$I$13:$I$112,IFERROR(MATCH(TEXT($B$10,"yyyymmdd")&"|"&$E$10&"|10",'EVENT ASSIGNMENT'!$K$2:$K$101,0),""))*INDEX('CONTRACT CALC'!$F$13:$F$112,IFERROR(MATCH(TEXT($B$10,"yyyymmdd")&"|"&$E$10&"|10",'EVENT ASSIGNMENT'!$K$2:$K$101,0),"")),"")) | E27: =IF(D27="","",D27*'CONTRACT CALC'!$B$4) | F27: =IF(OR(IFERROR(MATCH(TEXT($B$10,"yyyymmdd")&"|"&$E$10&"|10",'EVENT ASSIGNMENT'!$K$2:$K$101,0),"")="",B27=""),"",IFERROR(INDEX('CONTRACT CALC'!$H$13:$H$112,IFERROR(MATCH(TEXT($B$10,"yyyymmdd")&"|"&$E$10&"|10",'EVENT ASSIGNMENT'!$K$2:$K$101,0),""))*INDEX('CONTRACT CALC'!$F$13:$F$112,IFERROR(MATCH(TEXT($B$10,"yyyymmdd")&"|"&$E$10&"|10",'EVENT ASSIGNMENT'!$K$2:$K$101,0),"")),"")) | G27: =IF(F27="","",F27*'CONTRACT CALC'!$B$5) | H27: =IF(B27="","",N(E27)+N(G27)) | I27: =IF(OR(IFERROR(MATCH(TEXT($B$10,"yyyymmdd")&"|"&$E$10&"|10",'EVENT ASSIGNMENT'!$K$2:$K$101,0),"")="",B27=""),"",IF(COUNTIFS('TIPS DATA'!$A$2:$A$101,$B$10,'TIPS DATA'!$C$2:$C$101,$E$10,'TIPS DATA'!$D$2:$D$101,INDEX('EVENT ASSIGNMENT'!$C$2:$C$101,IFERROR(MATCH(TEXT($B$10,"yyyymmdd")&"|"&$E$10&"|10",'EVENT ASSIGNMENT'!$K$2:$K$101,0),"")))>0,SUMIFS('TIPS DATA'!$H$2:$H$101,'TIPS DATA'!$A$2:$A$101,$B$10,'TIPS DATA'!$C$2:$C$101,$E$10,'TIPS DATA'!$D$2:$D$101,INDEX('EVENT ASSIGNMENT'!$C$2:$C$101,IFERROR(MATCH(TEXT($B$10,"yyyymmdd")&"|"&$E$10&"|10",'EVENT ASSIGNMENT'!$K$2:$K$101,0),""))),SUMIFS('TIPS DATA'!$H$2:$H$101,'TIPS DATA'!$A$2:$A$101,$B$10,'TIPS DATA'!$C$2:$C$101,$E$10,'TIPS DATA'!$E$2:$E$101,INDEX('EVENT ASSIGNMENT'!$D$2:$D$101,IFERROR(MATCH(TEXT($B$10,"yyyymmdd")&"|"&$E$10&"|10",'EVENT ASSIGNMENT'!$K$2:$K$101,0),"")))))
A28: =IFERROR(MATCH(TEXT($B$10,"yyyymmdd")&"|"&$E$10&"|11",'EVENT ASSIGNMENT'!$K$2:$K$101,0),"") | B28: =IF(IFERROR(MATCH(TEXT($B$10,"yyyymmdd")&"|"&$E$10&"|11",'EVENT ASSIGNMENT'!$K$2:$K$101,0),"")="","",IFERROR(INDEX('EVENT ASSIGNMENT'!$D$2:$D$101,IFERROR(MATCH(TEXT($B$10,"yyyymmdd")&"|"&$E$10&"|11",'EVENT ASSIGNMENT'!$K$2:$K$101,0),"")),"")) | C28: =IF(OR(IFERROR(MATCH(TEXT($B$10,"yyyymmdd")&"|"&$E$10&"|11",'EVENT ASSIGNMENT'!$K$2:$K$101,0),"")="",B28=""),"",IFERROR(INDEX('CONTRACT CALC'!$G$13:$G$112,IFERROR(MATCH(TEXT($B$10,"yyyymmdd")&"|"&$E$10&"|11",'EVENT ASSIGNMENT'!$K$2:$K$101,0),""))*INDEX('CONTRACT CALC'!$F$13:$F$112,IFERROR(MATCH(TEXT($B$10,"yyyymmdd")&"|"&$E$10&"|11",'EVENT ASSIGNMENT'!$K$2:$K$101,0),"")),"")) | D28: =IF(OR(IFERROR(MATCH(TEXT($B$10,"yyyymmdd")&"|"&$E$10&"|11",'EVENT ASSIGNMENT'!$K$2:$K$101,0),"")="",B28=""),"",IFERROR(INDEX('CONTRACT CALC'!$I$13:$I$112,IFERROR(MATCH(TEXT($B$10,"yyyymmdd")&"|"&$E$10&"|11",'EVENT ASSIGNMENT'!$K$2:$K$101,0),""))*INDEX('CONTRACT CALC'!$F$13:$F$112,IFERROR(MATCH(TEXT($B$10,"yyyymmdd")&"|"&$E$10&"|11",'EVENT ASSIGNMENT'!$K$2:$K$101,0),"")),"")) | E28: =IF(D28="","",D28*'CONTRACT CALC'!$B$4) | F28: =IF(OR(IFERROR(MATCH(TEXT($B$10,"yyyymmdd")&"|"&$E$10&"|11",'EVENT ASSIGNMENT'!$K$2:$K$101,0),"")="",B28=""),"",IFERROR(INDEX('CONTRACT CALC'!$H$13:$H$112,IFERROR(MATCH(TEXT($B$10,"yyyymmdd")&"|"&$E$10&"|11",'EVENT ASSIGNMENT'!$K$2:$K$101,0),""))*INDEX('CONTRACT CALC'!$F$13:$F$112,IFERROR(MATCH(TEXT($B$10,"yyyymmdd")&"|"&$E$10&"|11",'EVENT ASSIGNMENT'!$K$2:$K$101,0),"")),"")) | G28: =IF(F28="","",F28*'CONTRACT CALC'!$B$5) | H28: =IF(B28="","",N(E28)+N(G28)) | I28: =IF(OR(IFERROR(MATCH(TEXT($B$10,"yyyymmdd")&"|"&$E$10&"|11",'EVENT ASSIGNMENT'!$K$2:$K$101,0),"")="",B28=""),"",IF(COUNTIFS('TIPS DATA'!$A$2:$A$101,$B$10,'TIPS DATA'!$C$2:$C$101,$E$10,'TIPS DATA'!$D$2:$D$101,INDEX('EVENT ASSIGNMENT'!$C$2:$C$101,IFERROR(MATCH(TEXT($B$10,"yyyymmdd")&"|"&$E$10&"|11",'EVENT ASSIGNMENT'!$K$2:$K$101,0),"")))>0,SUMIFS('TIPS DATA'!$H$2:$H$101,'TIPS DATA'!$A$2:$A$101,$B$10,'TIPS DATA'!$C$2:$C$101,$E$10,'TIPS DATA'!$D$2:$D$101,INDEX('EVENT ASSIGNMENT'!$C$2:$C$101,IFERROR(MATCH(TEXT($B$10,"yyyymmdd")&"|"&$E$10&"|11",'EVENT ASSIGNMENT'!$K$2:$K$101,0),""))),SUMIFS('TIPS DATA'!$H$2:$H$101,'TIPS DATA'!$A$2:$A$101,$B$10,'TIPS DATA'!$C$2:$C$101,$E$10,'TIPS DATA'!$E$2:$E$101,INDEX('EVENT ASSIGNMENT'!$D$2:$D$101,IFERROR(MATCH(TEXT($B$10,"yyyymmdd")&"|"&$E$10&"|11",'EVENT ASSIGNMENT'!$K$2:$K$101,0),"")))))
A29: =IFERROR(MATCH(TEXT($B$10,"yyyymmdd")&"|"&$E$10&"|12",'EVENT ASSIGNMENT'!$K$2:$K$101,0),"") | B29: =IF(IFERROR(MATCH(TEXT($B$10,"yyyymmdd")&"|"&$E$10&"|12",'EVENT ASSIGNMENT'!$K$2:$K$101,0),"")="","",IFERROR(INDEX('EVENT ASSIGNMENT'!$D$2:$D$101,IFERROR(MATCH(TEXT($B$10,"yyyymmdd")&"|"&$E$10&"|12",'EVENT ASSIGNMENT'!$K$2:$K$101,0),"")),"")) | C29: =IF(OR(IFERROR(MATCH(TEXT($B$10,"yyyymmdd")&"|"&$E$10&"|12",'EVENT ASSIGNMENT'!$K$2:$K$101,0),"")="",B29=""),"",IFERROR(INDEX('CONTRACT CALC'!$G$13:$G$112,IFERROR(MATCH(TEXT($B$10,"yyyymmdd")&"|"&$E$10&"|12",'EVENT ASSIGNMENT'!$K$2:$K$101,0),""))*INDEX('CONTRACT CALC'!$F$13:$F$112,IFERROR(MATCH(TEXT($B$10,"yyyymmdd")&"|"&$E$10&"|12",'EVENT ASSIGNMENT'!$K$2:$K$101,0),"")),"")) | D29: =IF(OR(IFERROR(MATCH(TEXT($B$10,"yyyymmdd")&"|"&$E$10&"|12",'EVENT ASSIGNMENT'!$K$2:$K$101,0),"")="",B29=""),"",IFERROR(INDEX('CONTRACT CALC'!$I$13:$I$112,IFERROR(MATCH(TEXT($B$10,"yyyymmdd")&"|"&$E$10&"|12",'EVENT ASSIGNMENT'!$K$2:$K$101,0),""))*INDEX('CONTRACT CALC'!$F$13:$F$112,IFERROR(MATCH(TEXT($B$10,"yyyymmdd")&"|"&$E$10&"|12",'EVENT ASSIGNMENT'!$K$2:$K$101,0),"")),"")) | E29: =IF(D29="","",D29*'CONTRACT CALC'!$B$4) | F29: =IF(OR(IFERROR(MATCH(TEXT($B$10,"yyyymmdd")&"|"&$E$10&"|12",'EVENT ASSIGNMENT'!$K$2:$K$101,0),"")="",B29=""),"",IFERROR(INDEX('CONTRACT CALC'!$H$13:$H$112,IFERROR(MATCH(TEXT($B$10,"yyyymmdd")&"|"&$E$10&"|12",'EVENT ASSIGNMENT'!$K$2:$K$101,0),""))*INDEX('CONTRACT CALC'!$F$13:$F$112,IFERROR(MATCH(TEXT($B$10,"yyyymmdd")&"|"&$E$10&"|12",'EVENT ASSIGNMENT'!$K$2:$K$101,0),"")),"")) | G29: =IF(F29="","",F29*'CONTRACT CALC'!$B$5) | H29: =IF(B29="","",N(E29)+N(G29)) | I29: =IF(OR(IFERROR(MATCH(TEXT($B$10,"yyyymmdd")&"|"&$E$10&"|12",'EVENT ASSIGNMENT'!$K$2:$K$101,0),"")="",B29=""),"",IF(COUNTIFS('TIPS DATA'!$A$2:$A$101,$B$10,'TIPS DATA'!$C$2:$C$101,$E$10,'TIPS DATA'!$D$2:$D$101,INDEX('EVENT ASSIGNMENT'!$C$2:$C$101,IFERROR(MATCH(TEXT($B$10,"yyyymmdd")&"|"&$E$10&"|12",'EVENT ASSIGNMENT'!$K$2:$K$101,0),"")))>0,SUMIFS('TIPS DATA'!$H$2:$H$101,'TIPS DATA'!$A$2:$A$101,$B$10,'TIPS DATA'!$C$2:$C$101,$E$10,'TIPS DATA'!$D$2:$D$101,INDEX('EVENT ASSIGNMENT'!$C$2:$C$101,IFERROR(MATCH(TEXT($B$10,"yyyymmdd")&"|"&$E$10&"|12",'EVENT ASSIGNMENT'!$K$2:$K$101,0),""))),SUMIFS('TIPS DATA'!$H$2:$H$101,'TIPS DATA'!$A$2:$A$101,$B$10,'TIPS DATA'!$C$2:$C$101,$E$10,'TIPS DATA'!$E$2:$E$101,INDEX('EVENT ASSIGNMENT'!$D$2:$D$101,IFERROR(MATCH(TEXT($B$10,"yyyymmdd")&"|"&$E$10&"|12",'EVENT ASSIGNMENT'!$K$2:$K$101,0),"")))))
A30: =IFERROR(MATCH(TEXT($B$10,"yyyymmdd")&"|"&$E$10&"|23",'EVENT ASSIGNMENT'!$K$2:$K$101,0),"") | B30: =IF(IFERROR(MATCH(TEXT($B$10,"yyyymmdd")&"|"&$E$10&"|23",'EVENT ASSIGNMENT'!$K$2:$K$101,0),"")="","",IFERROR(INDEX('EVENT ASSIGNMENT'!$D$2:$D$101,IFERROR(MATCH(TEXT($B$10,"yyyymmdd")&"|"&$E$10&"|23",'EVENT ASSIGNMENT'!$K$2:$K$101,0),"")),"")) | C30: =IF(OR(IFERROR(MATCH(TEXT($B$10,"yyyymmdd")&"|"&$E$10&"|23",'EVENT ASSIGNMENT'!$K$2:$K$101,0),"")="",B30=""),"",IFERROR(INDEX('CONTRACT CALC'!$G$13:$G$112,IFERROR(MATCH(TEXT($B$10,"yyyymmdd")&"|"&$E$10&"|23",'EVENT ASSIGNMENT'!$K$2:$K$101,0),""))*INDEX('CONTRACT CALC'!$F$13:$F$112,IFERROR(MATCH(TEXT($B$10,"yyyymmdd")&"|"&$E$10&"|23",'EVENT ASSIGNMENT'!$K$2:$K$101,0),"")),"")) | D30: =IF(OR(IFERROR(MATCH(TEXT($B$10,"yyyymmdd")&"|"&$E$10&"|23",'EVENT ASSIGNMENT'!$K$2:$K$101,0),"")="",B30=""),"",IFERROR(INDEX('CONTRACT CALC'!$I$13:$I$112,IFERROR(MATCH(TEXT($B$10,"yyyymmdd")&"|"&$E$10&"|23",'EVENT ASSIGNMENT'!$K$2:$K$101,0),""))*INDEX('CONTRACT CALC'!$F$13:$F$112,IFERROR(MATCH(TEXT($B$10,"yyyymmdd")&"|"&$E$10&"|23",'EVENT ASSIGNMENT'!$K$2:$K$101,0),"")),"")) | E30: =IF(D30="","",D30*'CONTRACT CALC'!$B$4) | F30: =IF(OR(IFERROR(MATCH(TEXT($B$10,"yyyymmdd")&"|"&$E$10&"|23",'EVENT ASSIGNMENT'!$K$2:$K$101,0),"")="",B30=""),"",IFERROR(INDEX('CONTRACT CALC'!$H$13:$H$112,IFERROR(MATCH(TEXT($B$10,"yyyymmdd")&"|"&$E$10&"|23",'EVENT ASSIGNMENT'!$K$2:$K$101,0),""))*INDEX('CONTRACT CALC'!$F$13:$F$112,IFERROR(MATCH(TEXT($B$10,"yyyymmdd")&"|"&$E$10&"|23",'EVENT ASSIGNMENT'!$K$2:$K$101,0),"")),"")) | G30: =IF(F30="","",F30*'CONTRACT CALC'!$B$5) | H30: =IF(B30="","",N(E30)+N(G30)) | I30: =IF(OR(IFERROR(MATCH(TEXT($B$10,"yyyymmdd")&"|"&$E$10&"|23",'EVENT ASSIGNMENT'!$K$2:$K$101,0),"")="",B30=""),"",IF(COUNTIFS('TIPS DATA'!$A$2:$A$101,$B$10,'TIPS DATA'!$C$2:$C$101,$E$10,'TIPS DATA'!$D$2:$D$101,INDEX('EVENT ASSIGNMENT'!$C$2:$C$101,IFERROR(MATCH(TEXT($B$10,"yyyymmdd")&"|"&$E$10&"|23",'EVENT ASSIGNMENT'!$K$2:$K$101,0),"")))>0,SUMIFS('TIPS DATA'!$H$2:$H$101,'TIPS DATA'!$A$2:$A$101,$B$10,'TIPS DATA'!$C$2:$C$101,$E$10,'TIPS DATA'!$D$2:$D$101,INDEX('EVENT ASSIGNMENT'!$C$2:$C$101,IFERROR(MATCH(TEXT($B$10,"yyyymmdd")&"|"&$E$10&"|23",'EVENT ASSIGNMENT'!$K$2:$K$101,0),""))),SUMIFS('TIPS DATA'!$H$2:$H$101,'TIPS DATA'!$A$2:$A$101,$B$10,'TIPS DATA'!$C$2:$C$101,$E$10,'TIPS DATA'!$E$2:$E$101,INDEX('EVENT ASSIGNMENT'!$D$2:$D$101,IFERROR(MATCH(TEXT($B$10,"yyyymmdd")&"|"&$E$10&"|23",'EVENT ASSIGNMENT'!$K$2:$K$101,0),"")))))
A31: =IFERROR(MATCH(TEXT($B$10,"yyyymmdd")&"|"&$E$10&"|24",'EVENT ASSIGNMENT'!$K$2:$K$101,0),"") | B31: =IF(IFERROR(MATCH(TEXT($B$10,"yyyymmdd")&"|"&$E$10&"|24",'EVENT ASSIGNMENT'!$K$2:$K$101,0),"")="","",IFERROR(INDEX('EVENT ASSIGNMENT'!$D$2:$D$101,IFERROR(MATCH(TEXT($B$10,"yyyymmdd")&"|"&$E$10&"|24",'EVENT ASSIGNMENT'!$K$2:$K$101,0),"")),"")) | C31: =IF(OR(IFERROR(MATCH(TEXT($B$10,"yyyymmdd")&"|"&$E$10&"|24",'EVENT ASSIGNMENT'!$K$2:$K$101,0),"")="",B31=""),"",IFERROR(INDEX('CONTRACT CALC'!$G$13:$G$112,IFERROR(MATCH(TEXT($B$10,"yyyymmdd")&"|"&$E$10&"|24",'EVENT ASSIGNMENT'!$K$2:$K$101,0),""))*INDEX('CONTRACT CALC'!$F$13:$F$112,IFERROR(MATCH(TEXT($B$10,"yyyymmdd")&"|"&$E$10&"|24",'EVENT ASSIGNMENT'!$K$2:$K$101,0),"")),"")) | D31: =IF(OR(IFERROR(MATCH(TEXT($B$10,"yyyymmdd")&"|"&$E$10&"|24",'EVENT ASSIGNMENT'!$K$2:$K$101,0),"")="",B31=""),"",IFERROR(INDEX('CONTRACT CALC'!$I$13:$I$112,IFERROR(MATCH(TEXT($B$10,"yyyymmdd")&"|"&$E$10&"|24",'EVENT ASSIGNMENT'!$K$2:$K$101,0),""))*INDEX('CONTRACT CALC'!$F$13:$F$112,IFERROR(MATCH(TEXT($B$10,"yyyymmdd")&"|"&$E$10&"|24",'EVENT ASSIGNMENT'!$K$2:$K$101,0),"")),"")) | E31: =IF(D31="","",D31*'CONTRACT CALC'!$B$4) | F31: =IF(OR(IFERROR(MATCH(TEXT($B$10,"yyyymmdd")&"|"&$E$10&"|24",'EVENT ASSIGNMENT'!$K$2:$K$101,0),"")="",B31=""),"",IFERROR(INDEX('CONTRACT CALC'!$H$13:$H$112,IFERROR(MATCH(TEXT($B$10,"yyyymmdd")&"|"&$E$10&"|24",'EVENT ASSIGNMENT'!$K$2:$K$101,0),""))*INDEX('CONTRACT CALC'!$F$13:$F$112,IFERROR(MATCH(TEXT($B$10,"yyyymmdd")&"|"&$E$10&"|24",'EVENT ASSIGNMENT'!$K$2:$K$101,0),"")),"")) | G31: =IF(F31="","",F31*'CONTRACT CALC'!$B$5) | H31: =IF(B31="","",N(E31)+N(G31)) | I31: =IF(OR(IFERROR(MATCH(TEXT($B$10,"yyyymmdd")&"|"&$E$10&"|24",'EVENT ASSIGNMENT'!$K$2:$K$101,0),"")="",B31=""),"",IF(COUNTIFS('TIPS DATA'!$A$2:$A$101,$B$10,'TIPS DATA'!$C$2:$C$101,$E$10,'TIPS DATA'!$D$2:$D$101,INDEX('EVENT ASSIGNMENT'!$C$2:$C$101,IFERROR(MATCH(TEXT($B$10,"yyyymmdd")&"|"&$E$10&"|24",'EVENT ASSIGNMENT'!$K$2:$K$101,0),"")))>0,SUMIFS('TIPS DATA'!$H$2:$H$101,'TIPS DATA'!$A$2:$A$101,$B$10,'TIPS DATA'!$C$2:$C$101,$E$10,'TIPS DATA'!$D$2:$D$101,INDEX('EVENT ASSIGNMENT'!$C$2:$C$101,IFERROR(MATCH(TEXT($B$10,"yyyymmdd")&"|"&$E$10&"|24",'EVENT ASSIGNMENT'!$K$2:$K$101,0),""))),SUMIFS('TIPS DATA'!$H$2:$H$101,'TIPS DATA'!$A$2:$A$101,$B$10,'TIPS DATA'!$C$2:$C$101,$E$10,'TIPS DATA'!$E$2:$E$101,INDEX('EVENT ASSIGNMENT'!$D$2:$D$101,IFERROR(MATCH(TEXT($B$10,"yyyymmdd")&"|"&$E$10&"|24",'EVENT ASSIGNMENT'!$K$2:$K$101,0),"")))))
A32: =IFERROR(MATCH(TEXT($B$10,"yyyymmdd")&"|"&$E$10&"|25",'EVENT ASSIGNMENT'!$K$2:$K$101,0),"") | B32: =IF(IFERROR(MATCH(TEXT($B$10,"yyyymmdd")&"|"&$E$10&"|25",'EVENT ASSIGNMENT'!$K$2:$K$101,0),"")="","",IFERROR(INDEX('EVENT ASSIGNMENT'!$D$2:$D$101,IFERROR(MATCH(TEXT($B$10,"yyyymmdd")&"|"&$E$10&"|25",'EVENT ASSIGNMENT'!$K$2:$K$101,0),"")),"")) | C32: =IF(OR(IFERROR(MATCH(TEXT($B$10,"yyyymmdd")&"|"&$E$10&"|25",'EVENT ASSIGNMENT'!$K$2:$K$101,0),"")="",B32=""),"",IFERROR(INDEX('CONTRACT CALC'!$G$13:$G$112,IFERROR(MATCH(TEXT($B$10,"yyyymmdd")&"|"&$E$10&"|25",'EVENT ASSIGNMENT'!$K$2:$K$101,0),""))*INDEX('CONTRACT CALC'!$F$13:$F$112,IFERROR(MATCH(TEXT($B$10,"yyyymmdd")&"|"&$E$10&"|25",'EVENT ASSIGNMENT'!$K$2:$K$101,0),"")),"")) | D32: =IF(OR(IFERROR(MATCH(TEXT($B$10,"yyyymmdd")&"|"&$E$10&"|25",'EVENT ASSIGNMENT'!$K$2:$K$101,0),"")="",B32=""),"",IFERROR(INDEX('CONTRACT CALC'!$I$13:$I$112,IFERROR(MATCH(TEXT($B$10,"yyyymmdd")&"|"&$E$10&"|25",'EVENT ASSIGNMENT'!$K$2:$K$101,0),""))*INDEX('CONTRACT CALC'!$F$13:$F$112,IFERROR(MATCH(TEXT($B$10,"yyyymmdd")&"|"&$E$10&"|25",'EVENT ASSIGNMENT'!$K$2:$K$101,0),"")),"")) | E32: =IF(D32="","",D32*'CONTRACT CALC'!$B$4) | F32: =IF(OR(IFERROR(MATCH(TEXT($B$10,"yyyymmdd")&"|"&$E$10&"|25",'EVENT ASSIGNMENT'!$K$2:$K$101,0),"")="",B32=""),"",IFERROR(INDEX('CONTRACT CALC'!$H$13:$H$112,IFERROR(MATCH(TEXT($B$10,"yyyymmdd")&"|"&$E$10&"|25",'EVENT ASSIGNMENT'!$K$2:$K$101,0),""))*INDEX('CONTRACT CALC'!$F$13:$F$112,IFERROR(MATCH(TEXT($B$10,"yyyymmdd")&"|"&$E$10&"|25",'EVENT ASSIGNMENT'!$K$2:$K$101,0),"")),"")) | G32: =IF(F32="","",F32*'CONTRACT CALC'!$B$5) | H32: =IF(B32="","",N(E32)+N(G32)) | I32: =IF(OR(IFERROR(MATCH(TEXT($B$10,"yyyymmdd")&"|"&$E$10&"|25",'EVENT ASSIGNMENT'!$K$2:$K$101,0),"")="",B32=""),"",IF(COUNTIFS('TIPS DATA'!$A$2:$A$101,$B$10,'TIPS DATA'!$C$2:$C$101,$E$10,'TIPS DATA'!$D$2:$D$101,INDEX('EVENT ASSIGNMENT'!$C$2:$C$101,IFERROR(MATCH(TEXT($B$10,"yyyymmdd")&"|"&$E$10&"|25",'EVENT ASSIGNMENT'!$K$2:$K$101,0),"")))>0,SUMIFS('TIPS DATA'!$H$2:$H$101,'TIPS DATA'!$A$2:$A$101,$B$10,'TIPS DATA'!$C$2:$C$101,$E$10,'TIPS DATA'!$D$2:$D$101,INDEX('EVENT ASSIGNMENT'!$C$2:$C$101,IFERROR(MATCH(TEXT($B$10,"yyyymmdd")&"|"&$E$10&"|25",'EVENT ASSIGNMENT'!$K$2:$K$101,0),""))),SUMIFS('TIPS DATA'!$H$2:$H$101,'TIPS DATA'!$A$2:$A$101,$B$10,'TIPS DATA'!$C$2:$C$101,$E$10,'TIPS DATA'!$E$2:$E$101,INDEX('EVENT ASSIGNMENT'!$D$2:$D$101,IFERROR(MATCH(TEXT($B$10,"yyyymmdd")&"|"&$E$10&"|25",'EVENT ASSIGNMENT'!$K$2:$K$101,0),"")))))
B33: TOTAL | C33: =SUM(C18:C32) -> 48024 | D33: =SUM(D18:D32) -> 32245 | E33: =SUM(E18:E32) -> 3224.5 | F33: =SUM(F18:F32) -> 15779 | G33: =SUM(G18:G32) -> 1262.32 | H33: =SUM(H18:H32) -> 4486.82 | I33: =SUM(I18:I32) -> 3421.74
B34: Location rows are filtered from EVENT ASSIGNMENT / CONTRACT CALC by Event Date + Payee. Location Total = Contractual Donation + Gratuities; commission rates are shown explicitly by sales category above.
G35: SUPPLEMENTAL PAYOUT:
B36: SETTLEMENT NOTES | G36: Sales Incentive | I36: =IFERROR(SUMIFS('SUPPLEMENTAL DATA'!$C$2:$C$101,'SUPPLEMENTAL DATA'!$A$2:$A$101,$B$10,'SUPPLEMENTAL DATA'!$B$2:$B$101,$E$10),0) -> 0
G37: Culinary - Cook Fee | I37: =IFERROR(SUMIFS('SUPPLEMENTAL DATA'!$D$2:$D$101,'SUPPLEMENTAL DATA'!$A$2:$A$101,$B$10,'SUPPLEMENTAL DATA'!$B$2:$B$101,$E$10),0) -> 0
G38: Minimum Donation | I38: =IFERROR(SUMIFS('SUPPLEMENTAL DATA'!$E$2:$E$101,'SUPPLEMENTAL DATA'!$A$2:$A$101,$B$10,'SUPPLEMENTAL DATA'!$B$2:$B$101,$E$10),0) -> 0
G39: Bonus (Other) | I39: =IFERROR(SUMIFS('SUPPLEMENTAL DATA'!$F$2:$F$101,'SUPPLEMENTAL DATA'!$A$2:$A$101,$B$10,'SUPPLEMENTAL DATA'!$B$2:$B$101,$E$10),0) -> 0
G40: Deductible POS Shortages | I40: =IFERROR(SUMIFS('SUPPLEMENTAL DATA'!$G$2:$G$101,'SUPPLEMENTAL DATA'!$A$2:$A$101,$B$10,'SUPPLEMENTAL DATA'!$B$2:$B$101,$E$10),0) -> 0
G41: Uniform / Staffing / Cleaning Fees | I41: =IFERROR(SUMIFS('SUPPLEMENTAL DATA'!$H$2:$H$101,'SUPPLEMENTAL DATA'!$A$2:$A$101,$B$10,'SUPPLEMENTAL DATA'!$B$2:$B$101,$E$10),0) -> 0
I42: =SUM(I36:I41) -> 0
B45: INTERNAL AUTHORIZATION CHECK REQUEST | E45: INTERNAL - ACCOUNTING GL ENTRY - SUMMARY
B46: Abigail Tenorio | C46: =TODAY() -> 46283 | E46: Group Commission | F46: 241 | 36127 | GL:611225 | G46: =H33 -> 4486.82
B47: Concessions Manager | E47: Gratuities | F47: 241 | 36127 | GL:212113 | G47: =I33 -> 3421.74
B48: Ray Velasquez | C48: =TODAY() -> 46283 | E48: Misc. (to be reclassed) | F48: 241 | 36127 | GL:673000 | G48: =SUM(I36:I40) -> 0
B49: Director of Operations | E49: Cleaning Fee - Expense | F49: 241 | 36127 | GL:674102 | G49: =I41 -> 0
B50: Evan E. Gonzales | C50: =TODAY() -> 46283
B51: Finance Manager

Sheet MSR RAW
A1: | Price Level - CATEGORIES - MSR Data Export | R1: University of New Mexico (2LEVY@UNM)
U2: 7.6250%
A3: Event:UNM FOOTBALL GAME 1 - 9/5 (252) Start Date:09/05/26 5:00:00 PM End Date:09/05/26 11:55:51 PM Discount Source:Default Price Level Detail Level:Summary
A4: Product | F4: Tax | W4: gap
A5: Code | D5: Name | E5: Standard Price | F5: Inclusive | H5: Exclusive | J5: SC | M5: Discount | O5: Quantity | Q5: Gross Amt | T5: Net
A6: Department: 36127 - CONCESSIONS
B7: Location: FB 100 - TRAILER N CONCOURSE
C8: Total: | F8: 0.00 | G8: 0.11 | I8: 0 | L8: 0.00 | N8: 226.00 | P8: 0.11 | S8: 0.00
C9: 312115 - N/A BEVERAGE SALES - TAXABLE Total: | F9: 0.00 | G9: 165.23 | I9: 0 | L9: 328.00 | N9: 380.00 | P9: 2,332.23 | S9: 2,167.00
C10: 313000 - FOOD SALES - TAXABLE Total: | F10: 0.00 | G10: 244.84 | I10: 0 | L10: 0.00 | N10: 234.00 | P10: 3,455.84 | S10: 3,211.00
C11: 313004 - LIQUOR SALES - TAXABLE Total: | F11: 0.00 | G11: 25.62 | I11: 0 | L11: 0.00 | N11: 21.00 | P11: 361.62 | S11: 336.00
C12: 313082 - BEER PACKAGED SALES Total: | F12: 0.00 | G12: 74.76 | I12: 0 | L12: -10.00 | N12: 74.00 | P12: 1,055.26 | S12: 980.50
B13: FB 100 - TRAILER N CONCOURSE Total: | F13: 0.00 | G13: 510.57 | I13: 0 | L13: 318.00 | N13: 935.00 | P13: 7,205.07 | S13: 6,694.50
B14: Location: FB 100B - MBP TRAILER N CONCOURSE
C15: Total: | F15: 0.00 | G15: 0.18 | I15: 0 | L15: 0.00 | N15: 242.00 | P15: 0.18 | S15: 0.00
C16: 312115 - N/A BEVERAGE SALES - TAXABLE Total: | F16: 0.00 | G16: 52.46 | I16: 0 | L16: 344.00 | N16: 172.00 | P16: 740.46 | S16: 688.00
C17: 313004 - LIQUOR SALES - TAXABLE Total: | F17: 0.00 | G17: 173.24 | I17: 0 | L17: 0.00 | N17: 142.00 | P17: 2,445.24 | S17: 2,272.00
C18: 313082 - BEER PACKAGED SALES Total: | F18: 0.00 | G18: 355.78 | I18: 0 | L18: 0.00 | N18: 365.00 | P18: 5,021.78 | S18: 4,666.00
B19: FB 100B - MBP TRAILER N CONCOURSE Total: | F19: 0.00 | G19: 581.66 | I19: 0 | L19: 344.00 | N19: 921.00 | P19: 8,207.66 | S19: 7,626.00
B20: Location: FB 101 - STADIUM SIPS SHACK SW
C21: Total: | F21: 0.00 | G21: 0.35 | I21: 0 | L21: 0.00 | N21: 319.00 | P21: 0.35 | S21: 0.00
C22: 312115 - N/A BEVERAGE SALES - TAXABLE Total: | F22: 0.00 | G22: 122.61 | I22: 0 | L22: 558.00 | N22: 279.00 | P22: 1,730.61 | S22: 1,608.00
C23: 313000 - FOOD SALES - TAXABLE Total: | F23: 0.00 | G23: 34.92 | I23: 0 | L23: 1.00 | N23: 129.00 | P23: 492.92 | S23: 458.00
C24: 313004 - LIQUOR SALES - TAXABLE Total: | F24: 0.00 | G24: 134.20 | I24: 0 | L24: 0.00 | N24: 110.00 | P24: 1,894.20 | S24: 1,760.00
C25: 313082 - BEER PACKAGED SALES Total: | F25: 0.00 | G25: 353.84 | I25: 0 | L25: 0.00 | N25: 351.00 | P25: 4,994.34 | S25: 4,640.50
C26: FF-312114 - N/A BEV SALE DISC. FAN FRIENDLY (CC36636) Total: | F26: 0.00 | G26: 58.26 | I26: 0 | L26: 0.00 | N26: 191.00 | P26: 822.26 | S26: 764.00
C27: FF-313076 - FOOD SALES DISC. FAN FRIENDLY (CC36636) Total: | F27: 0.00 | G27: 31.42 | I27: 0 | L27: 0.00 | N27: 103.00 | P27: 443.42 | S27: 412.00
B28: FB 101 - STADIUM SIPS SHACK SW Total: | F28: 0.00 | G28: 735.59 | I28: 0 | L28: 559.00 | N28: 1,482.00 | P28: 10,378.09 | S28: 9,642.50
B29: Location: FB 102 - TOWER SOUTH
C30: Total: | F30: 0.00 | G30: 0.30 | I30: 0 | L30: 0.00 | N30: 286.00 | P30: 0.30 | S30: 0.00
C31: 312115 - N/A BEVERAGE SALES - TAXABLE Total: | F31: 0.00 | G31: 97.75 | I31: 0 | L31: 308.00 | N31: 180.00 | P31: 1,379.75 | S31: 1,282.00
C32: 313000 - FOOD SALES - TAXABLE Total: | F32: 0.00 | G32: 155.70 | I32: 0 | L32: 57.00 | N32: 379.00 | P32: 2,197.70 | S32: 2,042.00
C33: 313004 - LIQUOR SALES - TAXABLE Total: | F33: 0.00 | G33: 37.82 | I33: 0 | L33: 0.00 | N33: 31.00 | P33: 533.82 | S33: 496.00
C34: 313082 - BEER PACKAGED SALES Total: | F34: 0.00 | G34: 141.33 | I34: 0 | L34: 0.00 | N34: 143.00 | P34: 1,994.83 | S34: 1,853.50
C35: FF-312114 - N/A BEV SALE DISC. FAN FRIENDLY (CC36636) Total: | F35: 0.00 | G35: 66.49 | I35: 0 | L35: 0.00 | N35: 218.00 | P35: 938.49 | S35: 872.00
C36: FF-313076 - FOOD SALES DISC. FAN FRIENDLY (CC36636) Total: | F36: 0.00 | G36: 56.12 | I36: 0 | L36: 368.00 | N36: 184.00 | P36: 792.12 | S36: 736.00
B37: FB 102 - TOWER SOUTH Total: | F37: 0.00 | G37: 555.51 | I37: 0 | L37: 733.00 | N37: 1,421.00 | P37: 7,837.01 | S37: 7,281.50
B38: Location: FB 103 - TOWER NORTH
C39: Total: | F39: 0.00 | G39: 0.29 | I39: 0 | L39: 0.00 | N39: 338.00 | P39: 0.29 | S39: 0.00
C40: 312115 - N/A BEVERAGE SALES - TAXABLE Total: | F40: 0.00 | G40: 92.11 | I40: 0 | L40: 288.00 | N40: 168.00 | P40: 1,300.11 | S40: 1,208.00
C41: 313000 - FOOD SALES - TAXABLE Total: | F41: 0.00 | G41: 140.22 | I41: 0 | L41: 39.00 | N41: 357.00 | P41: 1,979.22 | S41: 1,839.00
C42: 313004 - LIQUOR SALES - TAXABLE Total: | F42: 0.00 | G42: 43.92 | I42: 0 | L42: 0.00 | N42: 36.00 | P42: 619.92 | S42: 576.00
C43: 313082 - BEER PACKAGED SALES Total: | F43: 0.00 | G43: 191.43 | I43: 0 | L43: 0.00 | N43: 192.00 | P43: 2,701.93 | S43: 2,510.50
C44: FF-312114 - N/A BEV SALE DISC. FAN FRIENDLY (CC36636) Total: | F44: 0.00 | G44: 74.73 | I44: 0 | L44: 0.00 | N44: 245.00 | P44: 1,054.73 | S44: 980.00
C45: FF-313076 - FOOD SALES DISC. FAN FRIENDLY (CC36636) Total: | F45: 0.00 | G45: 39.96 | I45: 0 | L45: 242.00 | N45: 131.00 | P45: 563.96 | S45: 524.00
B46: FB 103 - TOWER NORTH Total: | F46: 0.00 | G46: 582.65 | I46: 0 | L46: 569.00 | N46: 1,467.00 | P46: 8,220.15 | S46: 7,637.50
B47: Location: FB 104 - RED RALLY NORTH WEST
C48: Total: | F48: 0.00 | G48: 1.00 | I48: 0 | L48: 0.00 | N48: 1,021.00 | P48: 1.00 | S48: 0.00
C49: 312115 - N/A BEVERAGE SALES - TAXABLE Total: | F49: 0.00 | G49: 608.40 | I49: 0 | L49: 2,208.00 | N49: 1,181.00 | P49: 8,587.40 | S49: 7,979.00
C50: 313000 - FOOD SALES - TAXABLE Total: | F50: 0.00 | G50: 881.98 | I50: 0 | L50: 200.00 | N50: 1,538.00 | P50: 12,448.98 | S50: 11,567.00
C51: 313004 - LIQUOR SALES - TAXABLE Total: | F51: 0.00 | G51: 180.56 | I51: 0 | L51: 0.00 | N51: 148.00 | P51: 2,548.56 | S51: 2,368.00
C52: 313082 - BEER PACKAGED SALES Total: | F52: 0.00 | G52: 367.83 | I52: 0 | L52: 0.00 | N52: 375.00 | P52: 5,191.83 | S52: 4,824.00
C53: FF-312114 - N/A BEV SALE DISC. FAN FRIENDLY (CC36636) Total: | F53: 0.00 | G53: 180.87 | I53: 0 | L53: 0.00 | N53: 593.00 | P53: 2,552.87 | S53: 2,372.00
C54: FF-313076 - FOOD SALES DISC. FAN FRIENDLY (CC36636) Total: | F54: 0.00 | G54: 272.67 | I54: 0 | L54: 1,788.00 | N54: 894.00 | P54: 3,848.67 | S54: 3,576.00
B55: FB 104 - RED RALLY NORTH WEST Total: | F55: 0.00 | G55: 2,493.31 | I55: 0 | L55: 4,196.00 | N55: 5,750.00 | P55: 35,179.31 | S55: 32,686.00
B56: Location: FB 105 - NW SPECIALTY - DAWG HOUSE
C57: Total: | F57: 0.00 | G57: 0.07 | I57: 0 | L57: 0.00 | N57: 202.00 | P57: 0.07 | S57: 0.00
C58: 312115 - N/A BEVERAGE SALES - TAXABLE Total: | F58: 0.00 | G58: 143.81 | I58: 0 | L58: 0.00 | N58: 238.00 | P58: 2,029.81 | S58: 1,886.00
C59: 313000 - FOOD SALES - TAXABLE Total: | F59: 0.00 | G59: 235.08 | I59: 0 | L59: 0.00 | N59: 251.00 | P59: 3,318.08 | S59: 3,083.00
C60: 313004 - LIQUOR SALES - TAXABLE Total: | F60: 0.00 | G60: 24.40 | I60: 0 | L60: 0.00 | N60: 20.00 | P60: 344.40 | S60: 320.00
C61: 313082 - BEER PACKAGED SALES Total: | F61: 0.00 | G61: 104.16 | I61: 0 | L61: 0.00 | N61: 101.00 | P61: 1,470.16 | S61: 1,366.00
C62: FF-313076 - FOOD SALES DISC. FAN FRIENDLY (CC36636) Total: | F62: 0.00 | G62: 20.13 | I62: 0 | L62: 0.00 | N62: 66.00 | P62: 284.13 | S62: 264.00
B63: FB 105 - NW SPECIALTY - DAWG HOUSE Total: | F63: 0.00 | G63: 527.64 | I63: 0 | L63: 0.00 | N63: 878.00 | P63: 7,446.64 | S63: 6,919.00
B64: Location: FB 106 - RED RALLY NORTH EAST
C65: Total: | F65: 0.00 | G65: 1.15 | I65: 0 | L65: 0.00 | N65: 1,123.00 | P65: 1.15 | S65: 0.00
C66: 312115 - N/A BEVERAGE SALES - TAXABLE Total: | F66: 0.00 | G66: 678.47 | I66: 0 | L66: 2,638.00 | N66: 1,498.00 | P66: 9,576.47 | S66: 8,898.00
C67: 313000 - FOOD SALES - TAXABLE Total: | F67: 0.00 | G67: 801.69 | I67: 0 | L67: 109.00 | N67: 1,451.00 | P67: 11,315.69 | S67: 10,514.00
C68: 313004 - LIQUOR SALES - TAXABLE Total: | F68: 0.00 | G68: 142.74 | I68: 0 | L68: 0.00 | N68: 117.00 | P68: 2,014.74 | S68: 1,872.00
C69: 313082 - BEER PACKAGED SALES Total: | F69: 0.00 | G69: 398.71 | I69: 0 | L69: 0.00 | N69: 399.00 | P69: 5,627.71 | S69: 5,229.00
C70: FF-313076 - FOOD SALES DISC. FAN FRIENDLY (CC36636) Total: | F70: 0.00 | G70: 219.60 | I70: 0 | L70: 1,304.00 | N70: 720.00 | P70: 3,099.60 | S70: 2,880.00
B71: FB 106 - RED RALLY NORTH EAST Total: | F71: 0.00 | G71: 2,242.37 | I71: 0 | L71: 4,051.00 | N71: 5,308.00 | P71: 31,635.37 | S71: 29,393.00
B72: Location: FB 107 - NE SPECIALTY - DAWG HOUSE
C73: Total: | F73: 0.00 | G73: 0.16 | I73: 0 | L73: 0.00 | N73: 229.00 | P73: 0.16 | S73: 0.00
C74: 312115 - N/A BEVERAGE SALES - TAXABLE Total: | F74: 0.00 | G74: 186.97 | I74: 0 | L74: 474.00 | N74: 429.00 | P74: 2,638.97 | S74: 2,452.00
C75: 313000 - FOOD SALES - TAXABLE Total: | F75: 0.00 | G75: 194.67 | I75: 0 | L75: 0.00 | N75: 239.00 | P75: 2,747.67 | S75: 2,553.00
C76: 313004 - LIQUOR SALES - TAXABLE Total: | F76: 0.00 | G76: 76.71 | I76: 0 | L76: 0.00 | N76: 65.00 | P76: 1,082.71 | S76: 1,006.00
C77: 313082 - BEER PACKAGED SALES Total: | F77: 0.00 | G77: 55.97 | I77: 0 | L77: -474.50 | N77: 54.00 | P77: 789.97 | S77: 734.00
B78: FB 107 - NE SPECIALTY - DAWG HOUSE Total: | F78: 0.00 | G78: 514.47 | I78: 0 | L78: -0.50 | N78: 1,016.00 | P78: 7,259.47 | S78: 6,745.00
B79: Location: FB 108 - GRAB N GO - NW
C80: Total: | F80: 0.00 | G80: 0.42 | I80: 0 | L80: 0.00 | N80: 677.00 | P80: 0.42 | S80: 0.00
C81: 312115 - N/A BEVERAGE SALES - TAXABLE Total: | F81: 0.00 | G81: 232.79 | I81: 0 | L81: 0.00 | N81: 434.00 | P81: 3,285.79 | S81: 3,053.00
C82: 313000 - FOOD SALES - TAXABLE Total: | F82: 0.00 | G82: 93.03 | I82: 0 | L82: 45.00 | N82: 265.00 | P82: 1,313.03 | S82: 1,220.00
C83: 313004 - LIQUOR SALES - TAXABLE Total: | F83: 0.00 | G83: 454.30 | I83: 0 | L83: 0.00 | N83: 379.00 | P83: 6,412.30 | S83: 5,958.00
C84: 313082 - BEER PACKAGED SALES Total: | F84: 0.00 | G84: 687.93 | I84: 0 | L84: 0.00 | N84: 703.00 | P84: 9,709.93 | S84: 9,022.00
C85: FF-312114 - N/A BEV SALE DISC. FAN FRIENDLY (CC36636) Total: | F85: 0.00 | G85: 185.75 | I85: 0 | L85: 0.00 | N85: 609.00 | P85: 2,621.75 | S85: 2,436.00
B86: FB 108 - GRAB N GO - NW Total: | F86: 0.00 | G86: 1,654.21 | I86: 0 | L86: 45.00 | N86: 3,067.00 | P86: 23,343.21 | S86: 21,689.00
B87: Location: FB 109 - MBP - NORTH EAST
C88: Total: | F88: 0.00 | G88: 0.26 | I88: 0 | L88: 0.00 | N88: 302.00 | P88: 0.26 | S88: 0.00
C89: 312115 - N/A BEVERAGE SALES - TAXABLE Total: | F89: 0.00 | G89: 35.38 | I89: 0 | L89: 232.00 | N89: 116.00 | P89: 499.38 | S89: 464.00
C90: 313004 - LIQUOR SALES - TAXABLE Total: | F90: 0.00 | G90: 202.52 | I90: 0 | L90: 0.00 | N90: 166.00 | P90: 2,858.52 | S90: 2,656.00
C91: 313082 - BEER PACKAGED SALES Total: | F91: 0.00 | G91: 482.93 | I91: 0 | L91: 0.00 | N91: 486.00 | P91: 6,816.43 | S91: 6,333.50
B92: FB 109 - MBP - NORTH EAST Total: | F92: 0.00 | G92: 721.09 | I92: 0 | L92: 232.00 | N92: 1,070.00 | P92: 10,174.59 | S92: 9,453.50
B93: Location: FB 110 - MBP - SHIVERS (NW)
C94: Total: | F94: 0.00 | G94: 0.25 | I94: 0 | L94: 0.00 | N94: 385.00 | P94: 0.25 | S94: 0.00
C95: 312115 - N/A BEVERAGE SALES - TAXABLE Total: | F95: 0.00 | G95: 43.31 | I95: 0 | L95: 284.00 | N95: 142.00 | P95: 611.31 | S95: 568.00
C96: 313004 - LIQUOR SALES - TAXABLE Total: | F96: 0.00 | G96: 294.02 | I96: 0 | L96: 0.00 | N96: 241.00 | P96: 4,150.02 | S96: 3,856.00
C97: 313082 - BEER PACKAGED SALES Total: | F97: 0.00 | G97: 651.98 | I97: 0 | L97: 0.00 | N97: 633.00 | P97: 9,202.48 | S97: 8,550.50
B98: FB 110 - MBP - SHIVERS (NW) Total: | F98: 0.00 | G98: 989.56 | I98: 0 | L98: 284.00 | N98: 1,401.00 | P98: 13,964.06 | S98: 12,974.50
B99: Location: FB 111 - MBP - NE PEPSI TRAILER
C100: Total: | F100: 0.00 | G100: 0.43 | I100: 0 | L100: 0.00 | N100: 415.00 | P100: 0.43 | S100: 0.00
...

Sheet CATEGORY MAP
A1: MyVenue Product Code | B1: Contract Class | C1: Description / Rule
A2: 312115 | B2: FOOD/NON-ALC | C2: N/A BEVERAGE SALES - TAXABLE
A3: 313000 | B3: FOOD/NON-ALC | C3: FOOD SALES - TAXABLE
A4: 313004 | B4: ALCOHOL | C4: LIQUOR SALES - TAXABLE
A5: 313082 | B5: ALCOHOL | C5: BEER PACKAGED SALES
A6: 313096 | B6: ALCOHOL | C6: WINE SALES - TAXABLE
A7: FF-312114 | B7: FOOD/NON-ALC | C7: Fan Friendly N/A beverage discount
A8: FF-313076 | B8: FOOD/NON-ALC | C8: Fan Friendly food discount
A9: 353008 | B9: FOOD/NON-ALC | C9: Subcontract income (food%)

Sheet MSR DATA
A1: Raw Row | B1: Event | C1: Department | D1: Location | E1: Product Code | F1: Product Name | G1: Contract Class | H1: Gross Amt | I1: Net
A2: 2 | B2: =IF('MSR RAW'!$A$3="","",'MSR RAW'!$A$3) -> Event:UNM FOOTBALL GAME 1 - 9/5 (252) Start Date:09/05/26 5:00:00 PM End Date:09/05/26 11:55:51 PM Discount Source:Default Price Level Detail Level:Summary | C2: =IF(LEFT(TRIM('MSR RAW'!A2),11)="Department:",TRIM('MSR RAW'!A2),"") | D2: =IF(LEFT(TRIM('MSR RAW'!B2),9)="Location:",TRIM(MID('MSR RAW'!B2,10,999)),"") | E2: =IF(AND(ISNUMBER(SEARCH(" - ",TRIM('MSR RAW'!C2))),RIGHT(TRIM('MSR RAW'!C2),6)="Total:"),LEFT(TRIM('MSR RAW'!C2),SEARCH(" - ",TRIM('MSR RAW'!C2))-1),"") | F2: =IF(E2="","",TRIM(MID(TRIM('MSR RAW'!C2),SEARCH(" - ",TRIM('MSR RAW'!C2))+3,LEN(TRIM('MSR RAW'!C2))-SEARCH(" - ",TRIM('MSR RAW'!C2))-9))) | G2: =IF(E2="","",IFERROR(VLOOKUP(E2,'CATEGORY MAP'!$A$2:$B$20,2,FALSE()),"REVIEW")) | H2: =IF(E2="","",IFERROR(VALUE(SUBSTITUTE('MSR RAW'!P2,",","")),0)) | I2: =IF(E2="","",IFERROR(VALUE(SUBSTITUTE('MSR RAW'!S2,",","")),0))
A3: 3 | B3: =IF('MSR RAW'!$A$3="","",'MSR RAW'!$A$3) -> Event:UNM FOOTBALL GAME 1 - 9/5 (252) Start Date:09/05/26 5:00:00 PM End Date:09/05/26 11:55:51 PM Discount Source:Default Price Level Detail Level:Summary | C3: =IF(LEFT(TRIM('MSR RAW'!A3),11)="Department:",TRIM('MSR RAW'!A3),C2) | D3: =IF(LEFT(TRIM('MSR RAW'!B3),9)="Location:",TRIM(MID('MSR RAW'!B3,10,999)),D2) | E3: =IF(AND(ISNUMBER(SEARCH(" - ",TRIM('MSR RAW'!C3))),RIGHT(TRIM('MSR RAW'!C3),6)="Total:"),LEFT(TRIM('MSR RAW'!C3),SEARCH(" - ",TRIM('MSR RAW'!C3))-1),"") | F3: =IF(E3="","",TRIM(MID(TRIM('MSR RAW'!C3),SEARCH(" - ",TRIM('MSR RAW'!C3))+3,LEN(TRIM('MSR RAW'!C3))-SEARCH(" - ",TRIM('MSR RAW'!C3))-9))) | G3: =IF(E3="","",IFERROR(VLOOKUP(E3,'CATEGORY MAP'!$A$2:$B$20,2,FALSE()),"REVIEW")) | H3: =IF(E3="","",IFERROR(VALUE(SUBSTITUTE('MSR RAW'!P3,",","")),0)) | I3: =IF(E3="","",IFERROR(VALUE(SUBSTITUTE('MSR RAW'!S3,",","")),0))
A4: 4 | B4: =IF('MSR RAW'!$A$3="","",'MSR RAW'!$A$3) -> Event:UNM FOOTBALL GAME 1 - 9/5 (252) Start Date:09/05/26 5:00:00 PM End Date:09/05/26 11:55:51 PM Discount Source:Default Price Level Detail Level:Summary | C4: =IF(LEFT(TRIM('MSR RAW'!A4),11)="Department:",TRIM('MSR RAW'!A4),C3) | D4: =IF(LEFT(TRIM('MSR RAW'!B4),9)="Location:",TRIM(MID('MSR RAW'!B4,10,999)),D3) | E4: =IF(AND(ISNUMBER(SEARCH(" - ",TRIM('MSR RAW'!C4))),RIGHT(TRIM('MSR RAW'!C4),6)="Total:"),LEFT(TRIM('MSR RAW'!C4),SEARCH(" - ",TRIM('MSR RAW'!C4))-1),"") | F4: =IF(E4="","",TRIM(MID(TRIM('MSR RAW'!C4),SEARCH(" - ",TRIM('MSR RAW'!C4))+3,LEN(TRIM('MSR RAW'!C4))-SEARCH(" - ",TRIM('MSR RAW'!C4))-9))) | G4: =IF(E4="","",IFERROR(VLOOKUP(E4,'CATEGORY MAP'!$A$2:$B$20,2,FALSE()),"REVIEW")) | H4: =IF(E4="","",IFERROR(VALUE(SUBSTITUTE('MSR RAW'!P4,",","")),0)) | I4: =IF(E4="","",IFERROR(VALUE(SUBSTITUTE('MSR RAW'!S4,",","")),0))
A5: 5 | B5: =IF('MSR RAW'!$A$3="","",'MSR RAW'!$A$3) -> Event:UNM FOOTBALL GAME 1 - 9/5 (252) Start Date:09/05/26 5:00:00 PM End Date:09/05/26 11:55:51 PM Discount Source:Default Price Level Detail Level:Summary | C5: =IF(LEFT(TRIM('MSR RAW'!A5),11)="Department:",TRIM('MSR RAW'!A5),C4) | D5: =IF(LEFT(TRIM('MSR RAW'!B5),9)="Location:",TRIM(MID('MSR RAW'!B5,10,999)),D4) | E5: =IF(AND(ISNUMBER(SEARCH(" - ",TRIM('MSR RAW'!C5))),RIGHT(TRIM('MSR RAW'!C5),6)="Total:"),LEFT(TRIM('MSR RAW'!C5),SEARCH(" - ",TRIM('MSR RAW'!C5))-1),"") | F5: =IF(E5="","",TRIM(MID(TRIM('MSR RAW'!C5),SEARCH(" - ",TRIM('MSR RAW'!C5))+3,LEN(TRIM('MSR RAW'!C5))-SEARCH(" - ",TRIM('MSR RAW'!C5))-9))) | G5: =IF(E5="","",IFERROR(VLOOKUP(E5,'CATEGORY MAP'!$A$2:$B$20,2,FALSE()),"REVIEW")) | H5: =IF(E5="","",IFERROR(VALUE(SUBSTITUTE('MSR RAW'!P5,",","")),0)) | I5: =IF(E5="","",IFERROR(VALUE(SUBSTITUTE('MSR RAW'!S5,",","")),0))
A6: 6 | B6: =IF('MSR RAW'!$A$3="","",'MSR RAW'!$A$3) -> Event:UNM FOOTBALL GAME 1 - 9/5 (252) Start Date:09/05/26 5:00:00 PM End Date:09/05/26 11:55:51 PM Discount Source:Default Price Level Detail Level:Summary | C6: =IF(LEFT(TRIM('MSR RAW'!A6),11)="Department:",TRIM('MSR RAW'!A6),C5) -> Department: 36127 - CONCESSIONS | D6: =IF(LEFT(TRIM('MSR RAW'!B6),9)="Location:",TRIM(MID('MSR RAW'!B6,10,999)),D5) | E6: =IF(AND(ISNUMBER(SEARCH(" - ",TRIM('MSR RAW'!C6))),RIGHT(TRIM('MSR RAW'!C6),6)="Total:"),LEFT(TRIM('MSR RAW'!C6),SEARCH(" - ",TRIM('MSR RAW'!C6))-1),"") | F6: =IF(E6="","",TRIM(MID(TRIM('MSR RAW'!C6),SEARCH(" - ",TRIM('MSR RAW'!C6))+3,LEN(TRIM('MSR RAW'!C6))-SEARCH(" - ",TRIM('MSR RAW'!C6))-9))) | G6: =IF(E6="","",IFERROR(VLOOKUP(E6,'CATEGORY MAP'!$A$2:$B$20,2,FALSE()),"REVIEW")) | H6: =IF(E6="","",IFERROR(VALUE(SUBSTITUTE('MSR RAW'!P6,",","")),0)) | I6: =IF(E6="","",IFERROR(VALUE(SUBSTITUTE('MSR RAW'!S6,",","")),0))
A7: 7 | B7: =IF('MSR RAW'!$A$3="","",'MSR RAW'!$A$3) -> Event:UNM FOOTBALL GAME 1 - 9/5 (252) Start Date:09/05/26 5:00:00 PM End Date:09/05/26 11:55:51 PM Discount Source:Default Price Level Detail Level:Summary | C7: =IF(LEFT(TRIM('MSR RAW'!A7),11)="Department:",TRIM('MSR RAW'!A7),C6) -> Department: 36127 - CONCESSIONS | D7: =IF(LEFT(TRIM('MSR RAW'!B7),9)="Location:",TRIM(MID('MSR RAW'!B7,10,999)),D6) -> FB 100 - TRAILER N CONCOURSE | E7: =IF(AND(ISNUMBER(SEARCH(" - ",TRIM('MSR RAW'!C7))),RIGHT(TRIM('MSR RAW'!C7),6)="Total:"),LEFT(TRIM('MSR RAW'!C7),SEARCH(" - ",TRIM('MSR RAW'!C7))-1),"") | F7: =IF(E7="","",TRIM(MID(TRIM('MSR RAW'!C7),SEARCH(" - ",TRIM('MSR RAW'!C7))+3,LEN(TRIM('MSR RAW'!C7))-SEARCH(" - ",TRIM('MSR RAW'!C7))-9))) | G7: =IF(E7="","",IFERROR(VLOOKUP(E7,'CATEGORY MAP'!$A$2:$B$20,2,FALSE()),"REVIEW")) | H7: =IF(E7="","",IFERROR(VALUE(SUBSTITUTE('MSR RAW'!P7,",","")),0)) | I7: =IF(E7="","",IFERROR(VALUE(SUBSTITUTE('MSR RAW'!S7,",","")),0))
A8: 8 | B8: =IF('MSR RAW'!$A$3="","",'MSR RAW'!$A$3) -> Event:UNM FOOTBALL GAME 1 - 9/5 (252) Start Date:09/05/26 5:00:00 PM End Date:09/05/26 11:55:51 PM Discount Source:Default Price Level Detail Level:Summary | C8: =IF(LEFT(TRIM('MSR RAW'!A8),11)="Department:",TRIM('MSR RAW'!A8),C7) -> Department: 36127 - CONCESSIONS | D8: =IF(LEFT(TRIM('MSR RAW'!B8),9)="Location:",TRIM(MID('MSR RAW'!B8,10,999)),D7) -> FB 100 - TRAILER N CONCOURSE | E8: =IF(AND(ISNUMBER(SEARCH(" - ",TRIM('MSR RAW'!C8))),RIGHT(TRIM('MSR RAW'!C8),6)="Total:"),LEFT(TRIM('MSR RAW'!C8),SEARCH(" - ",TRIM('MSR RAW'!C8))-1),"") | F8: =IF(E8="","",TRIM(MID(TRIM('MSR RAW'!C8),SEARCH(" - ",TRIM('MSR RAW'!C8))+3,LEN(TRIM('MSR RAW'!C8))-SEARCH(" - ",TRIM('MSR RAW'!C8))-9))) | G8: =IF(E8="","",IFERROR(VLOOKUP(E8,'CATEGORY MAP'!$A$2:$B$20,2,FALSE()),"REVIEW")) | H8: =IF(E8="","",IFERROR(VALUE(SUBSTITUTE('MSR RAW'!P8,",","")),0)) | I8: =IF(E8="","",IFERROR(VALUE(SUBSTITUTE('MSR RAW'!S8,",","")),0))
A9: 9 | B9: =IF('MSR RAW'!$A$3="","",'MSR RAW'!$A$3) -> Event:UNM FOOTBALL GAME 1 - 9/5 (252) Start Date:09/05/26 5:00:00 PM End Date:09/05/26 11:55:51 PM Discount Source:Default Price Level Detail Level:Summary | C9: =IF(LEFT(TRIM('MSR RAW'!A9),11)="Department:",TRIM('MSR RAW'!A9),C8) -> Department: 36127 - CONCESSIONS | D9: =IF(LEFT(TRIM('MSR RAW'!B9),9)="Location:",TRIM(MID('MSR RAW'!B9,10,999)),D8) -> FB 100 - TRAILER N CONCOURSE | E9: =IF(AND(ISNUMBER(SEARCH(" - ",TRIM('MSR RAW'!C9))),RIGHT(TRIM('MSR RAW'!C9),6)="Total:"),LEFT(TRIM('MSR RAW'!C9),SEARCH(" - ",TRIM('MSR RAW'!C9))-1),"") -> 312115 | F9: =IF(E9="","",TRIM(MID(TRIM('MSR RAW'!C9),SEARCH(" - ",TRIM('MSR RAW'!C9))+3,LEN(TRIM('MSR RAW'!C9))-SEARCH(" - ",TRIM('MSR RAW'!C9))-9))) -> N/A BEVERAGE SALES - TAXABLE | G9: =IF(E9="","",IFERROR(VLOOKUP(E9,'CATEGORY MAP'!$A$2:$B$20,2,FALSE()),"REVIEW")) -> FOOD/NON-ALC | H9: =IF(E9="","",IFERROR(VALUE(SUBSTITUTE('MSR RAW'!P9,",","")),0)) -> 2332.23 | I9: =IF(E9="","",IFERROR(VALUE(SUBSTITUTE('MSR RAW'!S9,",","")),0)) -> 2167
A10: 10 | B10: =IF('MSR RAW'!$A$3="","",'MSR RAW'!$A$3) -> Event:UNM FOOTBALL GAME 1 - 9/5 (252) Start Date:09/05/26 5:00:00 PM End Date:09/05/26 11:55:51 PM Discount Source:Default Price Level Detail Level:Summary | C10: =IF(LEFT(TRIM('MSR RAW'!A10),11)="Department:",TRIM('MSR RAW'!A10),C9) -> Department: 36127 - CONCESSIONS | D10: =IF(LEFT(TRIM('MSR RAW'!B10),9)="Location:",TRIM(MID('MSR RAW'!B10,10,999)),D9) -> FB 100 - TRAILER N CONCOURSE | E10: =IF(AND(ISNUMBER(SEARCH(" - ",TRIM('MSR RAW'!C10))),RIGHT(TRIM('MSR RAW'!C10),6)="Total:"),LEFT(TRIM('MSR RAW'!C10),SEARCH(" - ",TRIM('MSR RAW'!C10))-1),"") -> 313000 | F10: =IF(E10="","",TRIM(MID(TRIM('MSR RAW'!C10),SEARCH(" - ",TRIM('MSR RAW'!C10))+3,LEN(TRIM('MSR RAW'!C10))-SEARCH(" - ",TRIM('MSR RAW'!C10))-9))) -> FOOD SALES - TAXABLE | G10: =IF(E10="","",IFERROR(VLOOKUP(E10,'CATEGORY MAP'!$A$2:$B$20,2,FALSE()),"REVIEW")) -> FOOD/NON-ALC | H10: =IF(E10="","",IFERROR(VALUE(SUBSTITUTE('MSR RAW'!P10,",","")),0)) -> 3455.84 | I10: =IF(E10="","",IFERROR(VALUE(SUBSTITUTE('MSR RAW'!S10,",","")),0)) -> 3211
A11: 11 | B11: =IF('MSR RAW'!$A$3="","",'MSR RAW'!$A$3) -> Event:UNM FOOTBALL GAME 1 - 9/5 (252) Start Date:09/05/26 5:00:00 PM End Date:09/05/26 11:55:51 PM Discount Source:Default Price Level Detail Level:Summary | C11: =IF(LEFT(TRIM('MSR RAW'!A11),11)="Department:",TRIM('MSR RAW'!A11),C10) -> Department: 36127 - CONCESSIONS | D11: =IF(LEFT(TRIM('MSR RAW'!B11),9)="Location:",TRIM(MID('MSR RAW'!B11,10,999)),D10) -> FB 100 - TRAILER N CONCOURSE | E11: =IF(AND(ISNUMBER(SEARCH(" - ",TRIM('MSR RAW'!C11))),RIGHT(TRIM('MSR RAW'!C11),6)="Total:"),LEFT(TRIM('MSR RAW'!C11),SEARCH(" - ",TRIM('MSR RAW'!C11))-1),"") -> 313004 | F11: =IF(E11="","",TRIM(MID(TRIM('MSR RAW'!C11),SEARCH(" - ",TRIM('MSR RAW'!C11))+3,LEN(TRIM('MSR RAW'!C11))-SEARCH(" - ",TRIM('MSR RAW'!C11))-9))) -> LIQUOR SALES - TAXABLE | G11: =IF(E11="","",IFERROR(VLOOKUP(E11,'CATEGORY MAP'!$A$2:$B$20,2,FALSE()),"REVIEW")) -> ALCOHOL | H11: =IF(E11="","",IFERROR(VALUE(SUBSTITUTE('MSR RAW'!P11,",","")),0)) -> 361.62 | I11: =IF(E11="","",IFERROR(VALUE(SUBSTITUTE('MSR RAW'!S11,",","")),0)) -> 336
A12: 12 | B12: =IF('MSR RAW'!$A$3="","",'MSR RAW'!$A$3) -> Event:UNM FOOTBALL GAME 1 - 9/5 (252) Start Date:09/05/26 5:00:00 PM End Date:09/05/26 11:55:51 PM Discount Source:Default Price Level Detail Level:Summary | C12: =IF(LEFT(TRIM('MSR RAW'!A12),11)="Department:",TRIM('MSR RAW'!A12),C11) -> Department: 36127 - CONCESSIONS | D12: =IF(LEFT(TRIM('MSR RAW'!B12),9)="Location:",TRIM(MID('MSR RAW'!B12,10,999)),D11) -> FB 100 - TRAILER N CONCOURSE | E12: =IF(AND(ISNUMBER(SEARCH(" - ",TRIM('MSR RAW'!C12))),RIGHT(TRIM('MSR RAW'!C12),6)="Total:"),LEFT(TRIM('MSR RAW'!C12),SEARCH(" - ",TRIM('MSR RAW'!C12))-1),"") -> 313082 | F12: =IF(E12="","",TRIM(MID(TRIM('MSR RAW'!C12),SEARCH(" - ",TRIM('MSR RAW'!C12))+3,LEN(TRIM('MSR RAW'!C12))-SEARCH(" - ",TRIM('MSR RAW'!C12))-9))) -> BEER PACKAGED SALES | G12: =IF(E12="","",IFERROR(VLOOKUP(E12,'CATEGORY MAP'!$A$2:$B$20,2,FALSE()),"REVIEW")) -> ALCOHOL | H12: =IF(E12="","",IFERROR(VALUE(SUBSTITUTE('MSR RAW'!P12,",","")),0)) -> 1055.26 | I12: =IF(E12="","",IFERROR(VALUE(SUBSTITUTE('MSR RAW'!S12,",","")),0)) -> 980.5
A13: 13 | B13: =IF('MSR RAW'!$A$3="","",'MSR RAW'!$A$3) -> Event:UNM FOOTBALL GAME 1 - 9/5 (252) Start Date:09/05/26 5:00:00 PM End Date:09/05/26 11:55:51 PM Discount Source:Default Price Level Detail Level:Summary | C13: =IF(LEFT(TRIM('MSR RAW'!A13),11)="Department:",TRIM('MSR RAW'!A13),C12) -> Department: 36127 - CONCESSIONS | D13: =IF(LEFT(TRIM('MSR RAW'!B13),9)="Location:",TRIM(MID('MSR RAW'!B13,10,999)),D12) -> FB 100 - TRAILER N CONCOURSE | E13: =IF(AND(ISNUMBER(SEARCH(" - ",TRIM('MSR RAW'!C13))),RIGHT(TRIM('MSR RAW'!C13),6)="Total:"),LEFT(TRIM('MSR RAW'!C13),SEARCH(" - ",TRIM('MSR RAW'!C13))-1),"") | F13: =IF(E13="","",TRIM(MID(TRIM('MSR RAW'!C13),SEARCH(" - ",TRIM('MSR RAW'!C13))+3,LEN(TRIM('MSR RAW'!C13))-SEARCH(" - ",TRIM('MSR RAW'!C13))-9))) | G13: =IF(E13="","",IFERROR(VLOOKUP(E13,'CATEGORY MAP'!$A$2:$B$20,2,FALSE()),"REVIEW")) | H13: =IF(E13="","",IFERROR(VALUE(SUBSTITUTE('MSR RAW'!P13,",","")),0)) | I13: =IF(E13="","",IFERROR(VALUE(SUBSTITUTE('MSR RAW'!S13,",","")),0))
A14: 14 | B14: =IF('MSR RAW'!$A$3="","",'MSR RAW'!$A$3) -> Event:UNM FOOTBALL GAME 1 - 9/5 (252) Start Date:09/05/26 5:00:00 PM End Date:09/05/26 11:55:51 PM Discount Source:Default Price Level Detail Level:Summary | C14: =IF(LEFT(TRIM('MSR RAW'!A14),11)="Department:",TRIM('MSR RAW'!A14),C13) -> Department: 36127 - CONCESSIONS | D14: =IF(LEFT(TRIM('MSR RAW'!B14),9)="Location:",TRIM(MID('MSR RAW'!B14,10,999)),D13) -> FB 100B - MBP TRAILER N CONCOURSE | E14: =IF(AND(ISNUMBER(SEARCH(" - ",TRIM('MSR RAW'!C14))),RIGHT(TRIM('MSR RAW'!C14),6)="Total:"),LEFT(TRIM('MSR RAW'!C14),SEARCH(" - ",TRIM('MSR RAW'!C14))-1),"") | F14: =IF(E14="","",TRIM(MID(TRIM('MSR RAW'!C14),SEARCH(" - ",TRIM('MSR RAW'!C14))+3,LEN(TRIM('MSR RAW'!C14))-SEARCH(" - ",TRIM('MSR RAW'!C14))-9))) | G14: =IF(E14="","",IFERROR(VLOOKUP(E14,'CATEGORY MAP'!$A$2:$B$20,2,FALSE()),"REVIEW")) | H14: =IF(E14="","",IFERROR(VALUE(SUBSTITUTE('MSR RAW'!P14,",","")),0)) | I14: =IF(E14="","",IFERROR(VALUE(SUBSTITUTE('MSR RAW'!S14,",","")),0))
... A1000: 1000 | B1000: =IF('MSR RAW'!$A$3="","",'MSR RAW'!$A$3) -> Event:UNM FOOTBALL GAME 1 - 9/5 (252) Start Date:09/05/26 5:00:00 PM End Date:09/05/26 11:55:51 PM Discount Source:Default Price Level Detail Level:Summary | C1000: =IF(LEFT(TRIM('MSR RAW'!A1000),11)="Department:",TRIM('MSR RAW'!A1000),C999) -> Department: 36637 - SPECIALTY CONCESSIONS (VENDING) | D1000: =IF(LEFT(TRIM('MSR RAW'!B1000),9)="Location:",TRIM(MID('MSR RAW'!B1000,10,999)),D999) -> FB 155 - SUB ISLAND NOODLES | E1000: =IF(AND(ISNUMBER(SEARCH(" - ",TRIM('MSR RAW'!C1000))),RIGHT(TRIM('MSR RAW'!C1000),6)="Total:"),LEFT(TRIM('MSR RAW'!C1000),SEARCH(" - ",TRIM('MSR RAW'!C1000))-1),"") | F1000: =IF(E1000="","",TRIM(MID(TRIM('MSR RAW'!C1000),SEARCH(" - ",TRIM('MSR RAW'!C1000))+3,LEN(TRIM('MSR RAW'!C1000))-SEARCH(" - ",TRIM('MSR RAW'!C1000))-9))) | G1000: =IF(E1000="","",IFERROR(VLOOKUP(E1000,'CATEGORY MAP'!$A$2:$B$20,2,FALSE()),"REVIEW")) | H1000: =IF(E1000="","",IFERROR(VALUE(SUBSTITUTE('MSR RAW'!P1000,",","")),0)) | I1000: =IF(E1000="","",IFERROR(VALUE(SUBSTITUTE('MSR RAW'!S1000,",","")),0))

Sheet CONTRACT CALC
A1: CONTRACT DONATION CALCULATION — ASSIGNMENT-DRIVEN
A2: Rates and minimums are controlled here. Event-specific ownership comes from EVENT ASSIGNMENT; MSR sales come from MSR DATA.
A4: Food / Non-Alcoholic Rate | B4: 0.1
A5: Alcoholic Beverage Rate | B5: 0.08
A6: Minimum Donation / Event | B6: 200
A8: Core Logic | B8: Allocated Food/N-A Net × 10% + Allocated Alcohol Net × 8%
A9: Allocation Rule | B9: Each Event + Location + NPO assignment receives Allocation % of that location’s MSR net sales.
A10: Control | B10: Location allocations should total 100% when a location is operated by one or more NPOs.
A12: Event Date | B12: NPO | C12: Location ID | D12: Location Description | E12: MSR Location | F12: Allocation % | G12: MSR Total Net | H12: Alcohol Net | I12: Food / Non-Alc Net | J12: Allocated Net | K12: NEW CONTRACT DONATION | L12: Status
A13: =IF('EVENT ASSIGNMENT'!A2="","",'EVENT ASSIGNMENT'!A2) -> 46270 | B13: =IF('EVENT ASSIGNMENT'!F2="","",'EVENT ASSIGNMENT'!F2) -> ARVC | C13: =IF('EVENT ASSIGNMENT'!C2="","",'EVENT ASSIGNMENT'!C2) -> FB 106 | D13: =IF('EVENT ASSIGNMENT'!D2="","",'EVENT ASSIGNMENT'!D2) -> RED RALLY NORTH EAST | E13: =IF('EVENT ASSIGNMENT'!E2="","",'EVENT ASSIGNMENT'!E2) -> FB 106 - RED RALLY NORTH EAST | F13: =IF('EVENT ASSIGNMENT'!G2="","",'EVENT ASSIGNMENT'!G2) -> 1 | G13: =IF(E13="",0,SUMIFS('MSR DATA'!$I$2:$I$1001,'MSR DATA'!$D$2:$D$1001,E13)) -> 29393 | H13: =IF(E13="",0,SUMIFS('MSR DATA'!$I$2:$I$1001,'MSR DATA'!$D$2:$D$1001,E13,'MSR DATA'!$G$2:$G$1001,"ALCOHOL")) -> 7101 | I13: =G13-H13 -> 22292 | J13: =G13*IF(F13="",0,F13) -> 29393 | K13: =I13*IF(F13="",0,F13)*$B$4+H13*IF(F13="",0,F13)*$B$5 -> 2797.28 | L13: =IF(B13="","",IF(F13="","MISSING ALLOCATION",IF(ABS(SUMIFS($F$13:$F$112,$A$13:$A$112,A13,$C$13:$C$112,C13)-1)>0.0001,"REVIEW LOCATION ALLOCATION",IF(G13=0,"NO MSR SALES","OK")))) -> OK
A14: =IF('EVENT ASSIGNMENT'!A3="","",'EVENT ASSIGNMENT'!A3) -> 46270 | B14: =IF('EVENT ASSIGNMENT'!F3="","",'EVENT ASSIGNMENT'!F3) -> ARVC | C14: =IF('EVENT ASSIGNMENT'!C3="","",'EVENT ASSIGNMENT'!C3) -> FB 113 | D14: =IF('EVENT ASSIGNMENT'!D3="","",'EVENT ASSIGNMENT'!D3) -> MBP MINI MELTS (NW) | E14: =IF('EVENT ASSIGNMENT'!E3="","",'EVENT ASSIGNMENT'!E3) -> FB 113 - MBP - MINI MELTS (NW) | F14: =IF('EVENT ASSIGNMENT'!G3="","",'EVENT ASSIGNMENT'!G3) -> 1 | G14: =IF(E14="",0,SUMIFS('MSR DATA'!$I$2:$I$1001,'MSR DATA'!$D$2:$D$1001,E14)) -> 1930 | H14: =IF(E14="",0,SUMIFS('MSR DATA'!$I$2:$I$1001,'MSR DATA'!$D$2:$D$1001,E14,'MSR DATA'!$G$2:$G$1001,"ALCOHOL")) -> 0 | I14: =G14-H14 -> 1930 | J14: =G14*IF(F14="",0,F14) -> 1930 | K14: =I14*IF(F14="",0,F14)*$B$4+H14*IF(F14="",0,F14)*$B$5 -> 193 | L14: =IF(B14="","",IF(F14="","MISSING ALLOCATION",IF(ABS(SUMIFS($F$13:$F$112,$A$13:$A$112,A14,$C$13:$C$112,C14)-1)>0.0001,"REVIEW LOCATION ALLOCATION",IF(G14=0,"NO MSR SALES","OK")))) -> OK
A15: =IF('EVENT ASSIGNMENT'!A4="","",'EVENT ASSIGNMENT'!A4) -> 46270 | B15: =IF('EVENT ASSIGNMENT'!F4="","",'EVENT ASSIGNMENT'!F4) -> ARVC | C15: =IF('EVENT ASSIGNMENT'!C4="","",'EVENT ASSIGNMENT'!C4) -> FB 113B | D15: =IF('EVENT ASSIGNMENT'!D4="","",'EVENT ASSIGNMENT'!D4) -> MBP MINI MELTS (NE) | E15: =IF('EVENT ASSIGNMENT'!E4="","",'EVENT ASSIGNMENT'!E4) -> FB 113B - MBP - MINI MELTS (NE) | F15: =IF('EVENT ASSIGNMENT'!G4="","",'EVENT ASSIGNMENT'!G4) -> 1 | G15: =IF(E15="",0,SUMIFS('MSR DATA'!$I$2:$I$1001,'MSR DATA'!$D$2:$D$1001,E15)) -> 2330 | H15: =IF(E15="",0,SUMIFS('MSR DATA'!$I$2:$I$1001,'MSR DATA'!$D$2:$D$1001,E15,'MSR DATA'!$G$2:$G$1001,"ALCOHOL")) -> 0 | I15: =G15-H15 -> 2330 | J15: =G15*IF(F15="",0,F15) -> 2330 | K15: =I15*IF(F15="",0,F15)*$B$4+H15*IF(F15="",0,F15)*$B$5 -> 233 | L15: =IF(B15="","",IF(F15="","MISSING ALLOCATION",IF(ABS(SUMIFS($F$13:$F$112,$A$13:$A$112,A15,$C$13:$C$112,C15)-1)>0.0001,"REVIEW LOCATION ALLOCATION",IF(G15=0,"NO MSR SALES","OK")))) -> OK
A16: =IF('EVENT ASSIGNMENT'!A5="","",'EVENT ASSIGNMENT'!A5) -> 46270 | B16: =IF('EVENT ASSIGNMENT'!F5="","",'EVENT ASSIGNMENT'!F5) -> ARVC | C16: =IF('EVENT ASSIGNMENT'!C5="","",'EVENT ASSIGNMENT'!C5) -> FB 100B | D16: =IF('EVENT ASSIGNMENT'!D5="","",'EVENT ASSIGNMENT'!D5) -> MBP TRAILER N CONCOURSE | E16: =IF('EVENT ASSIGNMENT'!E5="","",'EVENT ASSIGNMENT'!E5) -> FB 100B - MBP TRAILER N CONCOURSE | F16: =IF('EVENT ASSIGNMENT'!G5="","",'EVENT ASSIGNMENT'!G5) -> 1 | G16: =IF(E16="",0,SUMIFS('MSR DATA'!$I$2:$I$1001,'MSR DATA'!$D$2:$D$1001,E16)) -> 7626 | H16: =IF(E16="",0,SUMIFS('MSR DATA'!$I$2:$I$1001,'MSR DATA'!$D$2:$D$1001,E16,'MSR DATA'!$G$2:$G$1001,"ALCOHOL")) -> 6938 | I16: =G16-H16 -> 688 | J16: =G16*IF(F16="",0,F16) -> 7626 | K16: =I16*IF(F16="",0,F16)*$B$4+H16*IF(F16="",0,F16)*$B$5 -> 623.84 | L16: =IF(B16="","",IF(F16="","MISSING ALLOCATION",IF(ABS(SUMIFS($F$13:$F$112,$A$13:$A$112,A16,$C$13:$C$112,C16)-1)>0.0001,"REVIEW LOCATION ALLOCATION",IF(G16=0,"NO MSR SALES","OK")))) -> OK
A17: =IF('EVENT ASSIGNMENT'!A6="","",'EVENT ASSIGNMENT'!A6) -> 46270 | B17: =IF('EVENT ASSIGNMENT'!F6="","",'EVENT ASSIGNMENT'!F6) -> ARVC | C17: =IF('EVENT ASSIGNMENT'!C6="","",'EVENT ASSIGNMENT'!C6) -> FB 107 | D17: =IF('EVENT ASSIGNMENT'!D6="","",'EVENT ASSIGNMENT'!D6) -> NE SPECIALTY DAWG O.G. | E17: =IF('EVENT ASSIGNMENT'!E6="","",'EVENT ASSIGNMENT'!E6) -> FB 107 - NE SPECIALTY - DAWG HOUSE | F17: =IF('EVENT ASSIGNMENT'!G6="","",'EVENT ASSIGNMENT'!G6) -> 1 | G17: =IF(E17="",0,SUMIFS('MSR DATA'!$I$2:$I$1001,'MSR DATA'!$D$2:$D$1001,E17)) -> 6745 | H17: =IF(E17="",0,SUMIFS('MSR DATA'!$I$2:$I$1001,'MSR DATA'!$D$2:$D$1001,E17,'MSR DATA'!$G$2:$G$1001,"ALCOHOL")) -> 1740 | I17: =G17-H17 -> 5005 | J17: =G17*IF(F17="",0,F17) -> 6745 | K17: =I17*IF(F17="",0,F17)*$B$4+H17*IF(F17="",0,F17)*$B$5 -> 639.7 | L17: =IF(B17="","",IF(F17="","MISSING ALLOCATION",IF(ABS(SUMIFS($F$13:$F$112,$A$13:$A$112,A17,$C$13:$C$112,C17)-1)>0.0001,"REVIEW LOCATION ALLOCATION",IF(G17=0,"NO MSR SALES","OK")))) -> OK
A18: =IF('EVENT ASSIGNMENT'!A7="","",'EVENT ASSIGNMENT'!A7) -> 46270 | B18: =IF('EVENT ASSIGNMENT'!F7="","",'EVENT ASSIGNMENT'!F7) -> AIRFORCE | C18: =IF('EVENT ASSIGNMENT'!C7="","",'EVENT ASSIGNMENT'!C7) -> PIT 104 | D18: =IF('EVENT ASSIGNMENT'!D7="","",'EVENT ASSIGNMENT'!D7) -> BURQUE BREWS (W) | E18: =IF('EVENT ASSIGNMENT'!E7="","",'EVENT ASSIGNMENT'!E7) -> PIT 104 - BURQUE BREWS (W) | F18: =IF('EVENT ASSIGNMENT'!G7="","",'EVENT ASSIGNMENT'!G7) -> 1 | G18: =IF(E18="",0,SUMIFS('MSR DATA'!$I$2:$I$1001,'MSR DATA'!$D$2:$D$1001,E18)) -> 0 | H18: =IF(E18="",0,SUMIFS('MSR DATA'!$I$2:$I$1001,'MSR DATA'!$D$2:$D$1001,E18,'MSR DATA'!$G$2:$G$1001,"ALCOHOL")) -> 0 | I18: =G18-H18 -> 0 | J18: =G18*IF(F18="",0,F18) -> 0 | K18: =I18*IF(F18="",0,F18)*$B$4+H18*IF(F18="",0,F18)*$B$5 -> 0 | L18: =IF(B18="","",IF(F18="","MISSING ALLOCATION",IF(ABS(SUMIFS($F$13:$F$112,$A$13:$A$112,A18,$C$13:$C$112,C18)-1)>0.0001,"REVIEW LOCATION ALLOCATION",IF(G18=0,"NO MSR SALES","OK")))) -> NO MSR SALES
A19: =IF('EVENT ASSIGNMENT'!A8="","",'EVENT ASSIGNMENT'!A8) -> 46270 | B19: =IF('EVENT ASSIGNMENT'!F8="","",'EVENT ASSIGNMENT'!F8) -> UNITED FIT | C19: =IF('EVENT ASSIGNMENT'!C8="","",'EVENT ASSIGNMENT'!C8) -> PIT 108 | D19: =IF('EVENT ASSIGNMENT'!D8="","",'EVENT ASSIGNMENT'!D8) -> HOOP & GO (J) | E19: =IF('EVENT ASSIGNMENT'!E8="","",'EVENT ASSIGNMENT'!E8) -> PIT 108 - HOOP & GO (J) | F19: =IF('EVENT ASSIGNMENT'!G8="","",'EVENT ASSIGNMENT'!G8) -> 1 | G19: =IF(E19="",0,SUMIFS('MSR DATA'!$I$2:$I$1001,'MSR DATA'!$D$2:$D$1001,E19)) -> 0 | H19: =IF(E19="",0,SUMIFS('MSR DATA'!$I$2:$I$1001,'MSR DATA'!$D$2:$D$1001,E19,'MSR DATA'!$G$2:$G$1001,"ALCOHOL")) -> 0 | I19: =G19-H19 -> 0 | J19: =G19*IF(F19="",0,F19) -> 0 | K19: =I19*IF(F19="",0,F19)*$B$4+H19*IF(F19="",0,F19)*$B$5 -> 0 | L19: =IF(B19="","",IF(F19="","MISSING ALLOCATION",IF(ABS(SUMIFS($F$13:$F$112,$A$13:$A$112,A19,$C$13:$C$112,C19)-1)>0.0001,"REVIEW LOCATION ALLOCATION",IF(G19=0,"NO MSR SALES","OK")))) -> NO MSR SALES
A20: =IF('EVENT ASSIGNMENT'!A9="","",'EVENT ASSIGNMENT'!A9) -> 46270 | B20: =IF('EVENT ASSIGNMENT'!F9="","",'EVENT ASSIGNMENT'!F9) -> DCVA | C20: =IF('EVENT ASSIGNMENT'!C9="","",'EVENT ASSIGNMENT'!C9) -> PIT 106 | D20: =IF('EVENT ASSIGNMENT'!D9="","",'EVENT ASSIGNMENT'!D9) -> LOUIE'S DAWG HOUSE (C) | E20: =IF('EVENT ASSIGNMENT'!E9="","",'EVENT ASSIGNMENT'!E9) -> PIT 106 - LOUIE'S DAWG HOUSE (C) | F20: =IF('EVENT ASSIGNMENT'!G9="","",'EVENT ASSIGNMENT'!G9) -> 1 | G20: =IF(E20="",0,SUMIFS('MSR DATA'!$I$2:$I$1001,'MSR DATA'!$D$2:$D$1001,E20)) -> 0 | H20: =IF(E20="",0,SUMIFS('MSR DATA'!$I$2:$I$1001,'MSR DATA'!$D$2:$D$1001,E20,'MSR DATA'!$G$2:$G$1001,"ALCOHOL")) -> 0 | I20: =G20-H20 -> 0 | J20: =G20*IF(F20="",0,F20) -> 0 | K20: =I20*IF(F20="",0,F20)*$B$4+H20*IF(F20="",0,F20)*$B$5 -> 0 | L20: =IF(B20="","",IF(F20="","MISSING ALLOCATION",IF(ABS(SUMIFS($F$13:$F$112,$A$13:$A$112,A20,$C$13:$C$112,C20)-1)>0.0001,"REVIEW LOCATION ALLOCATION",IF(G20=0,"NO MSR SALES","OK")))) -> NO MSR SALES
A21: =IF('EVENT ASSIGNMENT'!A10="","",'EVENT ASSIGNMENT'!A10) -> 46270 | B21: =IF('EVENT ASSIGNMENT'!F10="","",'EVENT ASSIGNMENT'!F10) -> DCVA | C21: =IF('EVENT ASSIGNMENT'!C10="","",'EVENT ASSIGNMENT'!C10) -> PIT 109 | D21: =IF('EVENT ASSIGNMENT'!D10="","",'EVENT ASSIGNMENT'!D10) -> ALLEYOOP (L) | E21: =IF('EVENT ASSIGNMENT'!E10="","",'EVENT ASSIGNMENT'!E10) -> PIT 109 - ALLEYOOP (L) | F21: =IF('EVENT ASSIGNMENT'!G10="","",'EVENT ASSIGNMENT'!G10) -> 1 | G21: =IF(E21="",0,SUMIFS('MSR DATA'!$I$2:$I$1001,'MSR DATA'!$D$2:$D$1001,E21)) -> 0 | H21: =IF(E21="",0,SUMIFS('MSR DATA'!$I$2:$I$1001,'MSR DATA'!$D$2:$D$1001,E21,'MSR DATA'!$G$2:$G$1001,"ALCOHOL")) -> 0 | I21: =G21-H21 -> 0 | J21: =G21*IF(F21="",0,F21) -> 0 | K21: =I21*IF(F21="",0,F21)*$B$4+H21*IF(F21="",0,F21)*$B$5 -> 0 | L21: =IF(B21="","",IF(F21="","MISSING ALLOCATION",IF(ABS(SUMIFS($F$13:$F$112,$A$13:$A$112,A21,$C$13:$C$112,C21)-1)>0.0001,"REVIEW LOCATION ALLOCATION",IF(G21=0,"NO MSR SALES","OK")))) -> NO MSR SALES
A22: =IF('EVENT ASSIGNMENT'!A11="","",'EVENT ASSIGNMENT'!A11) -> 46270 | B22: =IF('EVENT ASSIGNMENT'!F11="","",'EVENT ASSIGNMENT'!F11) -> DEL N CHEER | C22: =IF('EVENT ASSIGNMENT'!C11="","",'EVENT ASSIGNMENT'!C11) -> PIT 101 | D22: =IF('EVENT ASSIGNMENT'!D11="","",'EVENT ASSIGNMENT'!D11) -> A - POP & POUR | E22: =IF('EVENT ASSIGNMENT'!E11="","",'EVENT ASSIGNMENT'!E11) -> PIT 101 - A - POP & POUR | F22: =IF('EVENT ASSIGNMENT'!G11="","",'EVENT ASSIGNMENT'!G11) -> 1 | G22: =IF(E22="",0,SUMIFS('MSR DATA'!$I$2:$I$1001,'MSR DATA'!$D$2:$D$1001,E22)) -> 0 | H22: =IF(E22="",0,SUMIFS('MSR DATA'!$I$2:$I$1001,'MSR DATA'!$D$2:$D$1001,E22,'MSR DATA'!$G$2:$G$1001,"ALCOHOL")) -> 0 | I22: =G22-H22 -> 0 | J22: =G22*IF(F22="",0,F22) -> 0 | K22: =I22*IF(F22="",0,F22)*$B$4+H22*IF(F22="",0,F22)*$B$5 -> 0 | L22: =IF(B22="","",IF(F22="","MISSING ALLOCATION",IF(ABS(SUMIFS($F$13:$F$112,$A$13:$A$112,A22,$C$13:$C$112,C22)-1)>0.0001,"REVIEW LOCATION ALLOCATION",IF(G22=0,"NO MSR SALES","OK")))) -> REVIEW LOCATION ALLOCATION
A23: =IF('EVENT ASSIGNMENT'!A12="","",'EVENT ASSIGNMENT'!A12) -> 46270 | B23: =IF('EVENT ASSIGNMENT'!F12="","",'EVENT ASSIGNMENT'!F12) -> DEL N CHEER | C23: =IF('EVENT ASSIGNMENT'!C12="","",'EVENT ASSIGNMENT'!C12) -> PIT 101 | D23: =IF('EVENT ASSIGNMENT'!D12="","",'EVENT ASSIGNMENT'!D12) -> A - POP & POUR | E23: =IF('EVENT ASSIGNMENT'!E12="","",'EVENT ASSIGNMENT'!E12) -> PIT 101 - B - NACHOMAMA | F23: =IF('EVENT ASSIGNMENT'!G12="","",'EVENT ASSIGNMENT'!G12) -> 1 | G23: =IF(E23="",0,SUMIFS('MSR DATA'!$I$2:$I$1001,'MSR DATA'!$D$2:$D$1001,E23)) -> 0 | H23: =IF(E23="",0,SUMIFS('MSR DATA'!$I$2:$I$1001,'MSR DATA'!$D$2:$D$1001,E23,'MSR DATA'!$G$2:$G$1001,"ALCOHOL")) -> 0 | I23: =G23-H23 -> 0 | J23: =G23*IF(F23="",0,F23) -> 0 | K23: =I23*IF(F23="",0,F23)*$B$4+H23*IF(F23="",0,F23)*$B$5 -> 0 | L23: =IF(B23="","",IF(F23="","MISSING ALLOCATION",IF(ABS(SUMIFS($F$13:$F$112,$A$13:$A$112,A23,$C$13:$C$112,C23)-1)>0.0001,"REVIEW LOCATION ALLOCATION",IF(G23=0,"NO MSR SALES","OK")))) -> REVIEW LOCATION ALLOCATION
A24: =IF('EVENT ASSIGNMENT'!A13="","",'EVENT ASSIGNMENT'!A13) -> 46270 | B24: =IF('EVENT ASSIGNMENT'!F13="","",'EVENT ASSIGNMENT'!F13) -> RIO GRANDE RGHS | C24: =IF('EVENT ASSIGNMENT'!C13="","",'EVENT ASSIGNMENT'!C13) -> PIT 110 | D24: =IF('EVENT ASSIGNMENT'!D13="","",'EVENT ASSIGNMENT'!D13) -> PAPITAS (M) | E24: =IF('EVENT ASSIGNMENT'!E13="","",'EVENT ASSIGNMENT'!E13) -> PIT 110 - PAPITAS (M) | F24: =IF('EVENT ASSIGNMENT'!G13="","",'EVENT ASSIGNMENT'!G13) -> 1 | G24: =IF(E24="",0,SUMIFS('MSR DATA'!$I$2:$I$1001,'MSR DATA'!$D$2:$D$1001,E24)) -> 0 | H24: =IF(E24="",0,SUMIFS('MSR DATA'!$I$2:$I$1001,'MSR DATA'!$D$2:$D$1001,E24,'MSR DATA'!$G$2:$G$1001,"ALCOHOL")) -> 0 | I24: =G24-H24 -> 0 | J24: =G24*IF(F24="",0,F24) -> 0 | K24: =I24*IF(F24="",0,F24)*$B$4+H24*IF(F24="",0,F24)*$B$5 -> 0 | L24: =IF(B24="","",IF(F24="","MISSING ALLOCATION",IF(ABS(SUMIFS($F$13:$F$112,$A$13:$A$112,A24,$C$13:$C$112,C24)-1)>0.0001,"REVIEW LOCATION ALLOCATION",IF(G24=0,"NO MSR SALES","OK")))) -> NO MSR SALES
... A112: =IF('EVENT ASSIGNMENT'!A101="","",'EVENT ASSIGNMENT'!A101) | B112: =IF('EVENT ASSIGNMENT'!F101="","",'EVENT ASSIGNMENT'!F101) | C112: =IF('EVENT ASSIGNMENT'!C101="","",'EVENT ASSIGNMENT'!C101) | D112: =IF('EVENT ASSIGNMENT'!D101="","",'EVENT ASSIGNMENT'!D101) | E112: =IF('EVENT ASSIGNMENT'!E101="","",'EVENT ASSIGNMENT'!E101) | F112: =IF('EVENT ASSIGNMENT'!G101="","",'EVENT ASSIGNMENT'!G101) | G112: =IF(E112="",0,SUMIFS('MSR DATA'!$I$2:$I$1001,'MSR DATA'!$D$2:$D$1001,E112)) -> 0 | H112: =IF(E112="",0,SUMIFS('MSR DATA'!$I$2:$I$1001,'MSR DATA'!$D$2:$D$1001,E112,'MSR DATA'!$G$2:$G$1001,"ALCOHOL")) -> 0 | I112: =G112-H112 -> 0 | J112: =G112*IF(F112="",0,F112) -> 0 | K112: =I112*IF(F112="",0,F112)*$B$4+H112*IF(F112="",0,F112)*$B$5 -> 0 | L112: =IF(B112="","",IF(F112="","MISSING ALLOCATION",IF(ABS(SUMIFS($F$13:$F$112,$A$13:$A$112,A112,$C$13:$C$112,C112)-1)>0.0001,"REVIEW LOCATION ALLOCATION",IF(G112=0,"NO MSR SALES","OK"))))
B113: TOTAL | G113: =SUM(G13:G112) -> 54718.5 | H113: =SUM(H13:H112) -> 17095.5 | I113: =SUM(I13:I112) -> 37623 | J113: =SUM(J13:J112) -> 54718.5 | K113: =SUM(K13:K112) -> 5129.94

Sheet EVENT ASSIGNMENT
A1: Event Date | B1: Event Description | C1: Location ID | D1: Location Description | E1: MSR Location | F1: NPO | G1: Allocation % | H1: Assignment Status | I1: Notes | J1: Payee Seq | K1: Payout Lookup Key
A2: 46270 | B2: Football | C2: FB 106 | D2: RED RALLY NORTH EAST | E2: FB 106 - RED RALLY NORTH EAST | F2: ARVC | G2: 1 | H2: PROOF / INITIAL LOAD | J2: =IF(OR(A2="",F2=""),"",COUNTIFS($A$2:A2,A2,$F$2:F2,F2)) -> 1 | K2: =IF(OR(A2="",F2="",J2=""),"",TEXT(A2,"yyyymmdd")&"|"&F2&"|"&J2) -> 20260905|ARVC|1
A3: 46270 | B3: Football | C3: FB 113 | D3: MBP MINI MELTS (NW) | E3: FB 113 - MBP - MINI MELTS (NW) | F3: ARVC | G3: 1 | H3: PROOF / INITIAL LOAD | J3: =IF(OR(A3="",F3=""),"",COUNTIFS($A$2:A3,A3,$F$2:F3,F3)) -> 2 | K3: =IF(OR(A3="",F3="",J3=""),"",TEXT(A3,"yyyymmdd")&"|"&F3&"|"&J3) -> 20260905|ARVC|2
A4: 46270 | B4: Football | C4: FB 113B | D4: MBP MINI MELTS (NE) | E4: FB 113B - MBP - MINI MELTS (NE) | F4: ARVC | G4: 1 | H4: PROOF / INITIAL LOAD | J4: =IF(OR(A4="",F4=""),"",COUNTIFS($A$2:A4,A4,$F$2:F4,F4)) -> 3 | K4: =IF(OR(A4="",F4="",J4=""),"",TEXT(A4,"yyyymmdd")&"|"&F4&"|"&J4) -> 20260905|ARVC|3
A5: 46270 | B5: Football | C5: FB 100B | D5: MBP TRAILER N CONCOURSE | E5: FB 100B - MBP TRAILER N CONCOURSE | F5: ARVC | G5: 1 | H5: PROOF / INITIAL LOAD | J5: =IF(OR(A5="",F5=""),"",COUNTIFS($A$2:A5,A5,$F$2:F5,F5)) -> 4 | K5: =IF(OR(A5="",F5="",J5=""),"",TEXT(A5,"yyyymmdd")&"|"&F5&"|"&J5) -> 20260905|ARVC|4
A6: 46270 | B6: Football | C6: FB 107 | D6: NE SPECIALTY DAWG O.G. | E6: FB 107 - NE SPECIALTY - DAWG HOUSE | F6: ARVC | G6: 1 | H6: PROOF / INITIAL LOAD | J6: =IF(OR(A6="",F6=""),"",COUNTIFS($A$2:A6,A6,$F$2:F6,F6)) -> 5 | K6: =IF(OR(A6="",F6="",J6=""),"",TEXT(A6,"yyyymmdd")&"|"&F6&"|"&J6) -> 20260905|ARVC|5
A7: 46270 | B7: Football | C7: PIT 104 | D7: BURQUE BREWS (W) | E7: PIT 104 - BURQUE BREWS (W) | F7: AIRFORCE | G7: 1 | H7: PROOF / INITIAL LOAD | J7: =IF(OR(A7="",F7=""),"",COUNTIFS($A$2:A7,A7,$F$2:F7,F7)) -> 1 | K7: =IF(OR(A7="",F7="",J7=""),"",TEXT(A7,"yyyymmdd")&"|"&F7&"|"&J7) -> 20260905|AIRFORCE|1
A8: 46270 | B8: Football | C8: PIT 108 | D8: HOOP & GO (J) | E8: PIT 108 - HOOP & GO (J) | F8: UNITED FIT | G8: 1 | H8: PROOF / INITIAL LOAD | J8: =IF(OR(A8="",F8=""),"",COUNTIFS($A$2:A8,A8,$F$2:F8,F8)) -> 1 | K8: =IF(OR(A8="",F8="",J8=""),"",TEXT(A8,"yyyymmdd")&"|"&F8&"|"&J8) -> 20260905|UNITED FIT|1
A9: 46270 | B9: Football | C9: PIT 106 | D9: LOUIE'S DAWG HOUSE (C) | E9: PIT 106 - LOUIE'S DAWG HOUSE (C) | F9: DCVA | G9: 1 | H9: PROOF / INITIAL LOAD | J9: =IF(OR(A9="",F9=""),"",COUNTIFS($A$2:A9,A9,$F$2:F9,F9)) -> 1 | K9: =IF(OR(A9="",F9="",J9=""),"",TEXT(A9,"yyyymmdd")&"|"&F9&"|"&J9) -> 20260905|DCVA|1
A10: 46270 | B10: Football | C10: PIT 109 | D10: ALLEYOOP (L) | E10: PIT 109 - ALLEYOOP (L) | F10: DCVA | G10: 1 | H10: PROOF / INITIAL LOAD | J10: =IF(OR(A10="",F10=""),"",COUNTIFS($A$2:A10,A10,$F$2:F10,F10)) -> 2 | K10: =IF(OR(A10="",F10="",J10=""),"",TEXT(A10,"yyyymmdd")&"|"&F10&"|"&J10) -> 20260905|DCVA|2
A11: 46270 | B11: Football | C11: PIT 101 | D11: A - POP & POUR | E11: PIT 101 - A - POP & POUR | F11: DEL N CHEER | G11: 1 | H11: PROOF / INITIAL LOAD | J11: =IF(OR(A11="",F11=""),"",COUNTIFS($A$2:A11,A11,$F$2:F11,F11)) -> 1 | K11: =IF(OR(A11="",F11="",J11=""),"",TEXT(A11,"yyyymmdd")&"|"&F11&"|"&J11) -> 20260905|DEL N CHEER|1
A12: 46270 | B12: Football | C12: PIT 101 | D12: A - POP & POUR | E12: PIT 101 - B - NACHOMAMA | F12: DEL N CHEER | G12: 1 | H12: PROOF / INITIAL LOAD | J12: =IF(OR(A12="",F12=""),"",COUNTIFS($A$2:A12,A12,$F$2:F12,F12)) -> 2 | K12: =IF(OR(A12="",F12="",J12=""),"",TEXT(A12,"yyyymmdd")&"|"&F12&"|"&J12) -> 20260905|DEL N CHEER|2
A13: 46270 | B13: Football | C13: PIT 110 | D13: PAPITAS (M) | E13: PIT 110 - PAPITAS (M) | F13: RIO GRANDE RGHS | G13: 1 | H13: PROOF / INITIAL LOAD | J13: =IF(OR(A13="",F13=""),"",COUNTIFS($A$2:A13,A13,$F$2:F13,F13)) -> 1 | K13: =IF(OR(A13="",F13="",J13=""),"",TEXT(A13,"yyyymmdd")&"|"&F13&"|"&J13) -> 20260905|RIO GRANDE RGHS|1
A14: 46270 | B14: Football | C14: FB 100 | D14: TRAILER N CONCOURSE | E14: FB 100 - TRAILER N CONCOURSE | F14: VICTORY OUTREACH | G14: 1 | H14: PROOF / INITIAL LOAD | J14: =IF(OR(A14="",F14=""),"",COUNTIFS($A$2:A14,A14,$F$2:F14,F14)) -> 1 | K14: =IF(OR(A14="",F14="",J14=""),"",TEXT(A14,"yyyymmdd")&"|"&F14&"|"&J14) -> 20260905|VICTORY OUTREACH|1
J15: =IF(OR(A15="",F15=""),"",COUNTIFS($A$2:A15,A15,$F$2:F15,F15)) | K15: =IF(OR(A15="",F15="",J15=""),"",TEXT(A15,"yyyymmdd")&"|"&F15&"|"&J15)
J16: =IF(OR(A16="",F16=""),"",COUNTIFS($A$2:A16,A16,$F$2:F16,F16)) | K16: =IF(OR(A16="",F16="",J16=""),"",TEXT(A16,"yyyymmdd")&"|"&F16&"|"&J16)
J17: =IF(OR(A17="",F17=""),"",COUNTIFS($A$2:A17,A17,$F$2:F17,F17)) | K17: =IF(OR(A17="",F17="",J17=""),"",TEXT(A17,"yyyymmdd")&"|"&F17&"|"&J17)
J18: =IF(OR(A18="",F18=""),"",COUNTIFS($A$2:A18,A18,$F$2:F18,F18)) | K18: =IF(OR(A18="",F18="",J18=""),"",TEXT(A18,"yyyymmdd")&"|"&F18&"|"&J18)
J19: =IF(OR(A19="",F19=""),"",COUNTIFS($A$2:A19,A19,$F$2:F19,F19)) | K19: =IF(OR(A19="",F19="",J19=""),"",TEXT(A19,"yyyymmdd")&"|"&F19&"|"&J19)
J20: =IF(OR(A20="",F20=""),"",COUNTIFS($A$2:A20,A20,$F$2:F20,F20)) | K20: =IF(OR(A20="",F20="",J20=""),"",TEXT(A20,"yyyymmdd")&"|"&F20&"|"&J20)
J21: =IF(OR(A21="",F21=""),"",COUNTIFS($A$2:A21,A21,$F$2:F21,F21)) | K21: =IF(OR(A21="",F21="",J21=""),"",TEXT(A21,"yyyymmdd")&"|"&F21&"|"&J21)
J22: =IF(OR(A22="",F22=""),"",COUNTIFS($A$2:A22,A22,$F$2:F22,F22)) | K22: =IF(OR(A22="",F22="",J22=""),"",TEXT(A22,"yyyymmdd")&"|"&F22&"|"&J22)
J23: =IF(OR(A23="",F23=""),"",COUNTIFS($A$2:A23,A23,$F$2:F23,F23)) | K23: =IF(OR(A23="",F23="",J23=""),"",TEXT(A23,"yyyymmdd")&"|"&F23&"|"&J23)
J24: =IF(OR(A24="",F24=""),"",COUNTIFS($A$2:A24,A24,$F$2:F24,F24)) | K24: =IF(OR(A24="",F24="",J24=""),"",TEXT(A24,"yyyymmdd")&"|"&F24&"|"&J24)
J25: =IF(OR(A25="",F25=""),"",COUNTIFS($A$2:A25,A25,$F$2:F25,F25)) | K25: =IF(OR(A25="",F25="",J25=""),"",TEXT(A25,"yyyymmdd")&"|"&F25&"|"&J25)
J26: =IF(OR(A26="",F26=""),"",COUNTIFS($A$2:A26,A26,$F$2:F26,F26)) | K26: =IF(OR(A26="",F26="",J26=""),"",TEXT(A26,"yyyymmdd")&"|"&F26&"|"&J26)
... J101: =IF(OR(A101="",F101=""),"",COUNTIFS($A$2:A101,A101,$F$2:F101,F101)) | K101: =IF(OR(A101="",F101="",J101=""),"",TEXT(A101,"yyyymmdd")&"|"&F101&"|"&J101)

Sheet TIPS DATA
A1: Event Date | B1: Event Description | C1: NPO | D1: Location ID | E1: Location Description | F1: Gross Tips | G1: Allocation % | H1: Allocated Tips | I1: Source | J1: Notes
A2: 46270 | B2: Football | C2: ARVC | D2: FB 106 | E2: RED RALLY NORTH EAST | F2: 1905.76 | G2: 1 | H2: =F2*G2 -> 1905.76 | I2: ARVC - OG / proof | J2: Seeded from V7 ARVC gratuity line; replace with actual source when available.
A3: 46270 | B3: Football | C3: ARVC | D3: FB 113 | E3: MBP MINI MELTS (NW) | F3: 154.32 | G3: 1 | H3: =F3*G3 -> 154.32 | I3: ARVC - OG / proof | J3: Seeded from V7 ARVC gratuity line; replace with actual source when available.
A4: 46270 | B4: Football | C4: ARVC | D4: FB 113B | E4: MBP MINI MELTS (NE) | F4: 189 | G4: 1 | H4: =F4*G4 -> 189 | I4: ARVC - OG / proof | J4: Seeded from V7 ARVC gratuity line; replace with actual source when available.
A5: 46270 | B5: Football | C5: ARVC | D5: FB 100B | E5: MBP TRAILER N CONCOURSE | F5: 670.54 | G5: 1 | H5: =F5*G5 -> 670.54 | I5: ARVC - OG / proof | J5: Seeded from V7 ARVC gratuity line; replace with actual source when available.
A6: 46270 | B6: Football | C6: ARVC | D6: FB 107 | E6: NE SPECIALTY DAWG O.G. | F6: 502.12 | G6: 1 | H6: =F6*G6 -> 502.12 | I6: ARVC - OG / proof | J6: Seeded from V7 ARVC gratuity line; replace with actual source when available.

Sheet SUPPLEMENTAL DATA
A1: Event Date | B1: NPO | C1: Sales Incentive | D1: Culinary - Cook Fee | E1: Minimum Donation | F1: Bonus (Other) | G1: Deductible POS Shortages | H1: Uniform / Staffing / Cleaning Fees | I1: Notes
A2: 46270 | B2: ARVC | C2: 0 | D2: 0 | E2: 0 | F2: 0 | G2: 0 | H2: 0 | I2: Enter vendor-specific adjustments by Event + Payee. VENDOR PAYOUT reads these; it does not store them.
A3: 46270 | B3: AIRFORCE | C3: 0 | D3: 0 | E3: 0 | F3: 0 | G3: 0 | H3: 0
A4: 46270 | B4: UNITED FIT | C4: 0 | D4: 0 | E4: 0 | F4: 0 | G4: 0 | H4: 0
A5: 46270 | B5: DCVA | C5: 0 | D5: 0 | E5: 0 | F5: 0 | G5: 0 | H5: 0
A6: 46270 | B6: DEL N CHEER | C6: 0 | D6: 0 | E6: 0 | F6: 0 | G6: 0 | H6: 0
A7: 46270 | B7: RIO GRANDE RGHS | C7: 0 | D7: 0 | E7: 0 | F7: 0 | G7: 0 | H7: 0
A8: 46270 | B8: VICTORY OUTREACH | C8: 0 | D8: 0 | E8: 0 | F8: 0 | G8: 0 | H8: 0
